[{"layers":[{"index":0,"tiles":[{"x":5.5,"y":-8.5},{"x":4.5,"y":-8},{"x":6.5,"y":-8},{"x":3.5,"y":-7.5},{"x":5.5,"y":-7.5},{"x":7.5,"y":-7.5},{"x":2.5,"y":-7},{"x":4.5,"y":-7},{"x":6.5,"y":-7},{"x":8.5,"y":-7},{"x":1.5,"y":-6.5},{"x":3.5,"y":-6.5},{"x":7.5,"y":-6.5},{"x":9.5,"y":-6.5},{"x":2.5,"y":-6},{"x":5,"y":-6},{"x":6,"y":-6},{"x":8.5,"y":-6},{"x":4,"y":-5.5},{"x":7,"y":-5.5},{"x":9.5,"y":-5.5},{"x":1.5,"y":-5},{"x":2.5,"y":-5},{"x":5.5,"y":-5},{"x":8.5,"y":-5},{"x":4,"y":-4.5},{"x":7,"y":-4.5},{"x":9.5,"y":-4.5},{"x":2.5,"y":-4},{"x":5,"y":-4},{"x":6,"y":-4},{"x":8.5,"y":-4},{"x":1.5,"y":-3.5},{"x":3.5,"y":-3.5},{"x":7.5,"y":-3.5},{"x":9.5,"y":-3.5},{"x":2.5,"y":-3},{"x":4.5,"y":-3},{"x":6.5,"y":-3},{"x":8.5,"y":-3},{"x":3.5,"y":-2.5},{"x":5.5,"y":-2.5},{"x":7.5,"y":-2.5},{"x":4.5,"y":-2},{"x":6.5,"y":-2},{"x":5.5,"y":-1.5}]},{"index":1,"tiles":[{"x":5.5,"y":-8.5},{"x":4.5,"y":-8},{"x":6.5,"y":-8},{"x":3.5,"y":-7.5},{"x":5.5,"y":-7.5},{"x":7.5,"y":-7.5},{"x":2.5,"y":-7},{"x":4.5,"y":-7},{"x":6.5,"y":-7},{"x":8.5,"y":-7},{"x":1.5,"y":-6.5},{"x":3.5,"y":-6.5},{"x":7.5,"y":-6.5},{"x":9.5,"y":-6.5},{"x":2.5,"y":-6},{"x":5,"y":-6},{"x":6,"y":-6},{"x":8.5,"y":-6},{"x":1.5,"y":-5.5},{"x":4,"y":-5.5},{"x":7,"y":-5.5},{"x":9.5,"y":-5.5},{"x":2.5,"y":-5},{"x":5.5,"y":-5},{"x":8.5,"y":-5},{"x":1.5,"y":-4.5},{"x":4,"y":-4.5},{"x":7,"y":-4.5},{"x":9.5,"y":-4.5},{"x":2.5,"y":-4},{"x":5,"y":-4},{"x":6,"y":-4},{"x":8.5,"y":-4},{"x":1.5,"y":-3.5},{"x":3.5,"y":-3.5},{"x":7.5,"y":-3.5},{"x":9.5,"y":-3.5},{"x":2.5,"y":-3},{"x":4.5,"y":-3},{"x":6.5,"y":-3},{"x":8.5,"y":-3},{"x":3.5,"y":-2.5},{"x":5.5,"y":-2.5},{"x":7.5,"y":-2.5},{"x":4.5,"y":-2},{"x":6.5,"y":-2},{"x":5.5,"y":-1.5}]},{"index":2,"tiles":[{"x":5.5,"y":-8.5},{"x":4.5,"y":-8},{"x":6.5,"y":-8},{"x":3.5,"y":-7.5},{"x":5.5,"y":-7.5},{"x":7.5,"y":-7.5},{"x":2.5,"y":-7},{"x":4.5,"y":-7},{"x":6.5,"y":-7},{"x":8.5,"y":-7},{"x":1.5,"y":-6.5},{"x":3.5,"y":-6.5},{"x":7.5,"y":-6.5},{"x":9.5,"y":-6.5},{"x":2.5,"y":-6},{"x":5,"y":-6},{"x":6,"y":-6},{"x":8.5,"y":-6},{"x":1.5,"y":-5.5},{"x":4,"y":-5.5},{"x":7,"y":-5.5},{"x":9.5,"y":-5.5},{"x":2.5,"y":-5},{"x":5.5,"y":-5},{"x":8.5,"y":-5},{"x":1.5,"y":-4.5},{"x":4,"y":-4.5},{"x":7,"y":-4.5},{"x":9.5,"y":-4.5},{"x":2.5,"y":-4},{"x":5,"y":-4},{"x":6,"y":-4},{"x":8.5,"y":-4},{"x":1.5,"y":-3.5},{"x":3.5,"y":-3.5},{"x":7.5,"y":-3.5},{"x":9.5,"y":-3.5},{"x":2.5,"y":-3},{"x":4.5,"y":-3},{"x":6.5,"y":-3},{"x":8.5,"y":-3},{"x":3.5,"y":-2.5},{"x":5.5,"y":-2.5},{"x":7.5,"y":-2.5},{"x":4.5,"y":-2},{"x":6.5,"y":-2},{"x":5.5,"y":-1.5}]}],"seeds":["FhF6TCVs4DIoE6ZVA0Rx3BV2goKAZsUsgdV9oPUZHQcqFBOMYJR4hFKIjBqJFZaeihUOkCNtobh8n3h8XvNwIphJXaOBj6AEoNNNRHgoYuMJ1Ed2i9cgYsgFn4hm4RRShDF9RZl4Fzco"]},{"layers":[{"index":0,"tiles":[{"x":3,"y":-8.5},{"x":5.5,"y":-8.5},{"x":8,"y":-8.5},{"x":3,"y":-6.5},{"x":5.5,"y":-6.5},{"x":8,"y":-6.5},{"x":2.5,"y":-5.5},{"x":3.5,"y":-5.5},{"x":5,"y":-5.5},{"x":6,"y":-5.5},{"x":7.5,"y":-5.5},{"x":8.5,"y":-5.5},{"x":1.5,"y":-4.5},{"x":2.5,"y":-4.5},{"x":3.5,"y":-4.5},{"x":4.5,"y":-4.5},{"x":5.5,"y":-4.5},{"x":6.5,"y":-4.5},{"x":7.5,"y":-4.5},{"x":8.5,"y":-4.5},{"x":9.5,"y":-4.5},{"x":1.5,"y":-3.5},{"x":2.5,"y":-3.5},{"x":3.5,"y":-3.5},{"x":4.5,"y":-3.5},{"x":5.5,"y":-3.5},{"x":6.5,"y":-3.5},{"x":7.5,"y":-3.5},{"x":8.5,"y":-3.5},{"x":9.5,"y":-3.5},{"x":2.5,"y":-2.5},{"x":3.5,"y":-2.5},{"x":4.5,"y":-2.5},{"x":5.5,"y":-2.5},{"x":6.5,"y":-2.5},{"x":7.5,"y":-2.5},{"x":8.5,"y":-2.5},{"x":3,"y":-1.5},{"x":5,"y":-1.5},{"x":6,"y":-1.5},{"x":8,"y":-1.5},{"x":5.5,"y":-0.5}]},{"index":1,"tiles":[{"x":3,"y":-8.5},{"x":5.5,"y":-8.5},{"x":8,"y":-8.5},{"x":3,"y":-6.5},{"x":5.5,"y":-6.5},{"x":8,"y":-6.5},{"x":2.5,"y":-5.5},{"x":3.5,"y":-5.5},{"x":5,"y":-5.5},{"x":6,"y":-5.5},{"x":7.5,"y":-5.5},{"x":8.5,"y":-5.5},{"x":1.5,"y":-4.5},{"x":2.5,"y":-4.5},{"x":3.5,"y":-4.5},{"x":4.5,"y":-4.5},{"x":5.5,"y":-4.5},{"x":6.5,"y":-4.5},{"x":7.5,"y":-4.5},{"x":8.5,"y":-4.5},{"x":9.5,"y":-4.5},{"x":1.5,"y":-3.5},{"x":2.5,"y":-3.5},{"x":3.5,"y":-3.5},{"x":4.5,"y":-3.5},{"x":5.5,"y":-3.5},{"x":6.5,"y":-3.5},{"x":7.5,"y":-3.5},{"x":8.5,"y":-3.5},{"x":9.5,"y":-3.5},{"x":2.5,"y":-2.5},{"x":3.5,"y":-2.5},{"x":4.5,"y":-2.5},{"x":5.5,"y":-2.5},{"x":6.5,"y":-2.5},{"x":7.5,"y":-2.5},{"x":8.5,"y":-2.5},{"x":3,"y":-1.5},{"x":5,"y":-1.5},{"x":6,"y":-1.5},{"x":8,"y":-1.5},{"x":5.5,"y":-0.5}]},{"index":2,"tiles":[{"x":3,"y":-8.5},{"x":5.5,"y":-8.5},{"x":8,"y":-8.5},{"x":3,"y":-6.5},{"x":5.5,"y":-6.5},{"x":8,"y":-6.5},{"x":2.5,"y":-5.5},{"x":3.5,"y":-5.5},{"x":5,"y":-5.5},{"x":6,"y":-5.5},{"x":7.5,"y":-5.5},{"x":8.5,"y":-5.5},{"x":1.5,"y":-4.5},{"x":2.5,"y":-4.5},{"x":3.5,"y":-4.5},{"x":4.5,"y":-4.5},{"x":5.5,"y":-4.5},{"x":6.5,"y":-4.5},{"x":7.5,"y":-4.5},{"x":8.5,"y":-4.5},{"x":9.5,"y":-4.5},{"x":1.5,"y":-3.5},{"x":2.5,"y":-3.5},{"x":3.5,"y":-3.5},{"x":4.5,"y":-3.5},{"x":5.5,"y":-3.5},{"x":6.5,"y":-3.5},{"x":7.5,"y":-3.5},{"x":8.5,"y":-3.5},{"x":9.5,"y":-3.5},{"x":2.5,"y":-2.5},{"x":3.5,"y":-2.5},{"x":4.5,"y":-2.5},{"x":5.5,"y":-2.5},{"x":6.5,"y":-2.5},{"x":7.5,"y":-2.5},{"x":8.5,"y":-2.5},{"x":3,"y":-1.5},{"x":5,"y":-1.5},{"x":6,"y":-1.5},{"x":8,"y":-1.5},{"x":5.5,"y":-0.5}]}],"seeds":["X5WgXKhhCOg5zOEFhaAQhTJ1y2ceSVSeBMMF4SRG2daFEmlQINgYiDh61dM9oDiB3CQEnihxoCh+4CUGFCde3JA5HReAYaeA1jd4iheqXQiCFpZC3vJBnCRpXtBsHwgA"]},{"layers":[{"index":0,"tiles":[{"x":3.5,"y":-8.5},{"x":5.5,"y":-8.5},{"x":7.5,"y":-8.5},{"x":2.5,"y":-8},{"x":4.5,"y":-8},{"x":6.5,"y":-8},{"x":8.5,"y":-8},{"x":3.5,"y":-7.5},{"x":5.5,"y":-7.5},{"x":7.5,"y":-7.5},{"x":2.5,"y":-7},{"x":4.5,"y":-7},{"x":6.5,"y":-7},{"x":8.5,"y":-7},{"x":3.5,"y":-6.5},{"x":7.5,"y":-6.5},{"x":1.5,"y":-6},{"x":2.5,"y":-6},{"x":4.5,"y":-6},{"x":5.5,"y":-6},{"x":6.5,"y":-6},{"x":8.5,"y":-6},{"x":9.5,"y":-6},{"x":3.5,"y":-5.5},{"x":7.5,"y":-5.5},{"x":2.5,"y":-5},{"x":4.5,"y":-5},{"x":5.5,"y":-5},{"x":6.5,"y":-5},{"x":8.5,"y":-5},{"x":3.5,"y":-4.5},{"x":7.5,"y":-4.5},{"x":1.5,"y":-4},{"x":2.5,"y":-4},{"x":4.5,"y":-4},{"x":5.5,"y":-4},{"x":6.5,"y":-4},{"x":8.5,"y":-4},{"x":9.5,"y":-4},{"x":3.5,"y":-3.5},{"x":7.5,"y":-3.5},{"x":2.5,"y":-3},{"x":4.5,"y":-3},{"x":6.5,"y":-3},{"x":8.5,"y":-3},{"x":3.5,"y":-2.5},{"x":5.5,"y":-2.5},{"x":7.5,"y":-2.5},{"x":2.5,"y":-2},{"x":4.5,"y":-2},{"x":6.5,"y":-2},{"x":8.5,"y":-2},{"x":3.5,"y":-1.5},{"x":5.5,"y":-1.5},{"x":7.5,"y":-1.5}]},{"index":1,"tiles":[{"x":2.5,"y":-7.5},{"x":4.5,"y":-7.5},{"x":6.5,"y":-7.5},{"x":8.5,"y":-7.5},{"x":3.5,"y":-7},{"x":5.5,"y":-7},{"x":7.5,"y":-7},{"x":2.5,"y":-6.5},{"x":4.5,"y":-6.5},{"x":6.5,"y":-6.5},{"x":8.5,"y":-6.5},{"x":3.5,"y":-6},{"x":5.5,"y":-6},{"x":7.5,"y":-6},{"x":2.5,"y":-5.5},{"x":4.5,"y":-5.5},{"x":6.5,"y":-5.5},{"x":8.5,"y":-5.5},{"x":3.5,"y":-5},{"x":5.5,"y":-5},{"x":7.5,"y":-5},{"x":2.5,"y":-4.5},{"x":4.5,"y":-4.5},{"x":6.5,"y":-4.5},{"x":8.5,"y":-4.5},{"x":3.5,"y":-4},{"x":5.5,"y":-4},{"x":7.5,"y":-4},{"x":2.5,"y":-3.5},{"x":4.5,"y":-3.5},{"x":6.5,"y":-3.5},{"x":8.5,"y":-3.5},{"x":3.5,"y":-3},{"x":5.5,"y":-3},{"x":7.5,"y":-3},{"x":2.5,"y":-2.5},{"x":4.5,"y":-2.5},{"x":6.5,"y":-2.5},{"x":8.5,"y":-2.5}]},{"index":2,"tiles":[{"x":2.5,"y":-7},{"x":4.5,"y":-7},{"x":6.5,"y":-7},{"x":8.5,"y":-7},{"x":3.5,"y":-6.5},{"x":5.5,"y":-6.5},{"x":7.5,"y":-6.5},{"x":2.5,"y":-6},{"x":4.5,"y":-6},{"x":6.5,"y":-6},{"x":8.5,"y":-6},{"x":3.5,"y":-5.5},{"x":5.5,"y":-5.5},{"x":7.5,"y":-5.5},{"x":4.5,"y":-5},{"x":6.5,"y":-5},{"x":3.5,"y":-4.5},{"x":5.5,"y":-4.5},{"x":7.5,"y":-4.5},{"x":2.5,"y":-4},{"x":4.5,"y":-4},{"x":6.5,"y":-4},{"x":8.5,"y":-4},{"x":3.5,"y":-3.5},{"x":5.5,"y":-3.5},{"x":7.5,"y":-3.5},{"x":2.5,"y":-3},{"x":4.5,"y":-3},{"x":6.5,"y":-3},{"x":8.5,"y":-3}]},{"index":3,"tiles":[{"x":3.5,"y":-6},{"x":4.5,"y":-6},{"x":5.5,"y":-6},{"x":6.5,"y":-6},{"x":7.5,"y":-6},{"x":5.5,"y":-5},{"x":3.5,"y":-4},{"x":4.5,"y":-4},{"x":5.5,"y":-4},{"x":6.5,"y":-4},{"x":7.5,"y":-4}]},{"index":4,"tiles":[{"x":5.5,"y":-5.5},{"x":5.5,"y":-4.5}]},{"index":5,"tiles":[{"x":5.5,"y":-5}]}],"seeds":["YPeFXPdpItN4JicpCyoQ3RWJJyMkiCY6Qyh5k7JAzBYQXtBFhzUc2aKBYMZ9wzKCTcExHKhoBDZUVqQ8YSR8YbURXhJe4DNRqREEISVM6sRcIimKxsV1GCgyXRE4VRggoleCEOWFVAUA"]},{"layers":[{"index":0,"tiles":[{"x":5.5,"y":-9.5},{"x":5.5,"y":-8.5},{"x":5,"y":-7.5},{"x":6,"y":-7.5},{"x":4.5,"y":-6.5},{"x":5.5,"y":-6.5},{"x":6.5,"y":-6.5},{"x":3.5,"y":-6},{"x":7.5,"y":-6},{"x":2.5,"y":-5.5},{"x":4.5,"y":-5.5},{"x":5.5,"y":-5.5},{"x":6.5,"y":-5.5},{"x":8.5,"y":-5.5},{"x":0.5,"y":-5},{"x":1.5,"y":-5},{"x":3.5,"y":-5},{"x":7.5,"y":-5},{"x":9.5,"y":-5},{"x":10.5,"y":-5},{"x":2.5,"y":-4.5},{"x":4.5,"y":-4.5},{"x":5.5,"y":-4.5},{"x":6.5,"y":-4.5},{"x":8.5,"y":-4.5},{"x":3.5,"y":-4},{"x":7.5,"y":-4},{"x":4.5,"y":-3.5},{"x":5.5,"y":-3.5},{"x":6.5,"y":-3.5},{"x":5,"y":-2.5},{"x":6,"y":-2.5},{"x":5.5,"y":-1.5},{"x":5.5,"y":-0.5}]},{"index":1,"tiles":[{"x":5.5,"y":-9},{"x":5.5,"y":-8},{"x":5,"y":-7},{"x":6,"y":-7},{"x":4,"y":-6},{"x":5,"y":-6},{"x":6,"y":-6},{"x":7,"y":-6},{"x":3,"y":-5.5},{"x":8,"y":-5.5},{"x":1,"y":-5},{"x":2,"y":-5},{"x":4,"y":-5},{"x":5,"y":-5},{"x":6,"y":-5},{"x":7,"y":-5},{"x":9,"y":-5},{"x":10,"y":-5},{"x":3,"y":-4.5},{"x":8,"y":-4.5},{"x":4,"y":-4},{"x":5,"y":-4},{"x":6,"y":-4},{"x":7,"y":-4},{"x":5,"y":-3},{"x":6,"y":-3},{"x":5.5,"y":-2},{"x":5.5,"y":-1}]},{"index":2,"tiles":[{"x":5.5,"y":-8.5},{"x":5.5,"y":-7.5},{"x":5,"y":-6.5},{"x":6,"y":-6.5},{"x":3.5,"y":-5.5},{"x":4.5,"y":-5.5},{"x":5.5,"y":-5.5},{"x":6.5,"y":-5.5},{"x":7.5,"y":-5.5},{"x":1.5,"y":-5},{"x":2.5,"y":-5},{"x":8.5,"y":-5},{"x":9.5,"y":-5},{"x":3.5,"y":-4.5},{"x":4.5,"y":-4.5},{"x":5.5,"y":-4.5},{"x":6.5,"y":-4.5},{"x":7.5,"y":-4.5},{"x":5,"y":-3.5},{"x":6,"y":-3.5},{"x":5.5,"y":-2.5},{"x":5.5,"y":-1.5}]},{"index":3,"tiles":[{"x":5.5,"y":-8},{"x":5.5,"y":-7},{"x":5,"y":-6},{"x":6,"y":-6},{"x":4,"y":-5.5},{"x":7,"y":-5.5},{"x":2,"y":-5},{"x":3,"y":-5},{"x":5,"y":-5},{"x":6,"y":-5},{"x":8,"y":-5},{"x":9,"y":-5},{"x":4,"y":-4.5},{"x":7,"y":-4.5},{"x":5,"y":-4},{"x":6,"y":-4},{"x":5.5,"y":-3},{"x":5.5,"y":-2}]},{"index":4,"tiles":[{"x":5.5,"y":-7.5},{"x":5.5,"y":-6.5},{"x":4.5,"y":-5.5},{"x":5.5,"y":-5.5},{"x":6.5,"y":-5.5},{"x":2.5,"y":-5},{"x":3.5,"y":-5},{"x":7.5,"y":-5},{"x":8.5,"y":-5},{"x":4.5,"y":-4.5},{"x":5.5,"y":-4.5},{"x":6.5,"y":-4.5},{"x":5.5,"y":-3.5},{"x":5.5,"y":-2.5}]},{"index":5,"tiles":[{"x":5.5,"y":-7},{"x":5.5,"y":-6},{"x":3,"y":-5},{"x":4,"y":-5},{"x":5,"y":-5},{"x":6,"y":-5},{"x":7,"y":-5},{"x":8,"y":-5},{"x":5.5,"y":-4},{"x":5.5,"y":-3}]},{"index":6,"tiles":[{"x":5.5,"y":-6.5},{"x":5.5,"y":-5.5},{"x":3.5,"y":-5},{"x":4.5,"y":-5},{"x":6.5,"y":-5},{"x":7.5,"y":-5},{"x":5.5,"y":-4.5},{"x":5.5,"y":-3.5}]},{"index":7,"tiles":[{"x":5.5,"y":-6},{"x":4,"y":-5},{"x":5,"y":-5},{"x":6,"y":-5},{"x":7,"y":-5},{"x":5.5,"y":-4}]},{"index":8,"tiles":[{"x":5.5,"y":-5.5},{"x":4.5,"y":-5},{"x":6.5,"y":-5},{"x":5.5,"y":-4.5}]}],"seeds":["ymcpDugxnlMwCJdwSQE2YEMJVEd+1vBoihZ83HKVQlVh4fAwAwQtTtGJ4nB1CBpNKghKoLlNI0FwC0VwkwJ+YUZ9HAF6lRgGQsAVneBFYhcy2DKF4BZynhSKhygeorV01uI1oNF81ZkZThoG"]},{"layers":[{"index":0,"tiles":[{"x":7.5,"y":-9.5},{"x":8.5,"y":-9.5},{"x":9.5,"y":-9.5},{"x":1.5,"y":-8.5},{"x":2.5,"y":-8.5},{"x":3.5,"y":-8.5},{"x":4.5,"y":-8.5},{"x":5.5,"y":-8.5},{"x":6.5,"y":-8.5},{"x":7.5,"y":-8.5},{"x":8.5,"y":-8.5},{"x":9.5,"y":-8.5},{"x":1.5,"y":-7.5},{"x":2.5,"y":-7.5},{"x":3.5,"y":-7.5},{"x":4.5,"y":-7.5},{"x":5.5,"y":-7.5},{"x":6.5,"y":-7.5},{"x":7.5,"y":-7.5},{"x":8.5,"y":-7.5},{"x":9.5,"y":-7.5},{"x":4.5,"y":-6.5},{"x":5.5,"y":-6.5},{"x":6.5,"y":-6.5},{"x":7.5,"y":-6.5},{"x":8.5,"y":-6.5},{"x":9.5,"y":-6.5},{"x":4.5,"y":-5.5},{"x":5.5,"y":-5.5},{"x":6.5,"y":-5.5},{"x":1.5,"y":-4.5},{"x":2.5,"y":-4.5},{"x":3.5,"y":-4.5},{"x":4.5,"y":-4.5},{"x":5.5,"y":-4.5},{"x":6.5,"y":-4.5},{"x":1.5,"y":-3.5},{"x":2.5,"y":-3.5},{"x":3.5,"y":-3.5},{"x":4.5,"y":-3.5},{"x":5.5,"y":-3.5},{"x":6.5,"y":-3.5},{"x":7.5,"y":-3.5},{"x":8.5,"y":-3.5},{"x":9.5,"y":-3.5},{"x":1.5,"y":-2.5},{"x":2.5,"y":-2.5},{"x":3.5,"y":-2.5},{"x":4.5,"y":-2.5},{"x":5.5,"y":-2.5},{"x":6.5,"y":-2.5},{"x":7.5,"y":-2.5},{"x":8.5,"y":-2.5},{"x":9.5,"y":-2.5},{"x":1.5,"y":-1.5},{"x":2.5,"y":-1.5},{"x":3.5,"y":-1.5}]},{"index":1,"tiles":[{"x":7.5,"y":-9.5},{"x":8.5,"y":-9.5},{"x":9.5,"y":-9.5},{"x":1.5,"y":-8.5},{"x":2.5,"y":-8.5},{"x":3.5,"y":-8.5},{"x":7.5,"y":-8.5},{"x":8.5,"y":-8.5},{"x":9.5,"y":-8.5},{"x":1.5,"y":-7.5},{"x":2.5,"y":-7.5},{"x":3.5,"y":-7.5},{"x":4.5,"y":-7.5},{"x":5.5,"y":-7.5},{"x":6.5,"y":-7.5},{"x":7.5,"y":-7.5},{"x":8.5,"y":-7.5},{"x":9.5,"y":-7.5},{"x":4.5,"y":-6.5},{"x":5.5,"y":-6.5},{"x":6.5,"y":-6.5},{"x":4.5,"y":-5.5},{"x":5.5,"y":-5.5},{"x":6.5,"y":-5.5},{"x":4.5,"y":-4.5},{"x":5.5,"y":-4.5},{"x":6.5,"y":-4.5},{"x":1.5,"y":-3.5},{"x":2.5,"y":-3.5},{"x":3.5,"y":-3.5},{"x":4.5,"y":-3.5},{"x":5.5,"y":-3.5},{"x":6.5,"y":-3.5},{"x":7.5,"y":-3.5},{"x":8.5,"y":-3.5},{"x":9.5,"y":-3.5},{"x":1.5,"y":-2.5},{"x":2.5,"y":-2.5},{"x":3.5,"y":-2.5},{"x":7.5,"y":-2.5},{"x":8.5,"y":-2.5},{"x":9.5,"y":-2.5},{"x":1.5,"y":-1.5},{"x":2.5,"y":-1.5},{"x":3.5,"y":-1.5}]},{"index":2,"tiles":[{"x":7.5,"y":-9.5},{"x":8.5,"y":-9.5},{"x":9.5,"y":-9.5},{"x":1.5,"y":-8.5},{"x":2.5,"y":-8.5},{"x":3.5,"y":-8.5},{"x":7.5,"y":-8.5},{"x":8.5,"y":-8.5},{"x":9.5,"y":-8.5},{"x":1.5,"y":-7.5},{"x":2.5,"y":-7.5},{"x":3.5,"y":-7.5},{"x":7.5,"y":-3.5},{"x":8.5,"y":-3.5},{"x":9.5,"y":-3.5},{"x":1.5,"y":-2.5},{"x":2.5,"y":-2.5},{"x":3.5,"y":-2.5},{"x":7.5,"y":-2.5},{"x":8.5,"y":-2.5},{"x":9.5,"y":-2.5},{"x":1.5,"y":-1.5},{"x":2.5,"y":-1.5},{"x":3.5,"y":-1.5}]},{"index":3,"tiles":[{"x":7.5,"y":-9.5},{"x":8.5,"y":-9.5},{"x":9.5,"y":-9.5},{"x":1.5,"y":-8.5},{"x":2.5,"y":-8.5},{"x":3.5,"y":-8.5},{"x":7.5,"y":-8.5},{"x":8.5,"y":-8.5},{"x":9.5,"y":-8.5},{"x":1.5,"y":-7.5},{"x":2.5,"y":-7.5},{"x":3.5,"y":-7.5},{"x":7.5,"y":-3.5},{"x":8.5,"y":-3.5},{"x":9.5,"y":-3.5},{"x":1.5,"y":-2.5},{"x":2.5,"y":-2.5},{"x":3.5,"y":-2.5},{"x":7.5,"y":-2.5},{"x":8.5,"y":-2.5},{"x":9.5,"y":-2.5},{"x":1.5,"y":-1.5},{"x":2.5,"y":-1.5},{"x":3.5,"y":-1.5}]}],"seeds":["CAh+V1iK2ZcxBOh9CCNwXPhVDSgQk9hIqKgOIhQGw8OITxUdiKU5HCheR+EMwceE2OIs3tRpHJly2OR9EhVaXbV5SEMNYgh2lnkqFRd6yTeFoDMuYrQoneGFAgGFFGiAmVAoivUFQbYQ2/eBVNc1yQIA"]},{"layers":[{"index":0,"tiles":[{"x":5.5,"y":-9.5},{"x":4.5,"y":-9},{"x":6.5,"y":-9},{"x":5.5,"y":-8.5},{"x":3.5,"y":-8},{"x":4.5,"y":-8},{"x":6.5,"y":-8},{"x":7.5,"y":-8},{"x":5.5,"y":-7.5},{"x":3,"y":-7},{"x":8,"y":-7},{"x":5.5,"y":-6.5},{"x":2.5,"y":-6},{"x":4.5,"y":-6},{"x":6.5,"y":-6},{"x":8.5,"y":-6},{"x":5.5,"y":-5.5},{"x":2.5,"y":-5},{"x":8.5,"y":-5},{"x":5.5,"y":-4.5},{"x":2.5,"y":-4},{"x":4.5,"y":-4},{"x":6.5,"y":-4},{"x":8.5,"y":-4},{"x":5.5,"y":-3.5},{"x":3,"y":-3},{"x":8,"y":-3},{"x":5.5,"y":-2.5},{"x":3.5,"y":-2},{"x":4.5,"y":-2},{"x":6.5,"y":-2},{"x":7.5,"y":-2},{"x":5.5,"y":-1.5},{"x":4.5,"y":-1},{"x":6.5,"y":-1},{"x":5.5,"y":-0.5}]},{"index":1,"tiles":[{"x":5.5,"y":-9.5},{"x":4.5,"y":-9},{"x":6.5,"y":-9},{"x":5.5,"y":-8.5},{"x":3.5,"y":-8},{"x":4.5,"y":-8},{"x":6.5,"y":-8},{"x":7.5,"y":-8},{"x":5.5,"y":-7.5},{"x":3,"y":-7},{"x":8,"y":-7},{"x":5.5,"y":-6.5},{"x":2.5,"y":-6},{"x":4.5,"y":-6},{"x":6.5,"y":-6},{"x":8.5,"y":-6},{"x":5.5,"y":-5.5},{"x":2.5,"y":-5},{"x":8.5,"y":-5},{"x":5.5,"y":-4.5},{"x":2.5,"y":-4},{"x":4.5,"y":-4},{"x":6.5,"y":-4},{"x":8.5,"y":-4},{"x":5.5,"y":-3.5},{"x":3,"y":-3},{"x":8,"y":-3},{"x":5.5,"y":-2.5},{"x":3.5,"y":-2},{"x":4.5,"y":-2},{"x":6.5,"y":-2},{"x":7.5,"y":-2},{"x":5.5,"y":-1.5},{"x":4.5,"y":-1},{"x":6.5,"y":-1},{"x":5.5,"y":-0.5}]},{"index":2,"tiles":[{"x":5.5,"y":-8.5},{"x":5.5,"y":-7.5},{"x":5.5,"y":-6.5},{"x":5.5,"y":-5.5},{"x":5.5,"y":-4.5},{"x":5.5,"y":-3.5},{"x":5.5,"y":-2.5},{"x":5.5,"y":-1.5}]}],"seeds":["YEMhCAgugmGpItRwk+IdIcilxzlimFF1JJF9YFV0FqFMDsOFYbGY3SU4AXd5EBiiYsYM4vA8XtmJ1Bd4"]},{"layers":[{"index":0,"tiles":[{"x":4.5,"y":-9},{"x":6.5,"y":-9},{"x":4,"y":-8},{"x":5,"y":-8},{"x":6,"y":-8},{"x":7,"y":-8},{"x":3.5,"y":-7},{"x":4.5,"y":-7},{"x":5.5,"y":-7},{"x":6.5,"y":-7},{"x":7.5,"y":-7},{"x":3,"y":-6},{"x":4,"y":-6},{"x":5,"y":-6},{"x":6,"y":-6},{"x":7,"y":-6},{"x":8,"y":-6},{"x":2.5,"y":-5},{"x":3.5,"y":-5},{"x":4.5,"y":-5},{"x":5.5,"y":-5},{"x":6.5,"y":-5},{"x":7.5,"y":-5},{"x":8.5,"y":-5},{"x":2,"y":-4},{"x":3,"y":-4},{"x":4,"y":-4},{"x":5,"y":-4},{"x":6,"y":-4},{"x":7,"y":-4},{"x":8,"y":-4},{"x":9,"y":-4},{"x":3.5,"y":-3},{"x":7.5,"y":-3},{"x":3.5,"y":-2},{"x":7.5,"y":-2},{"x":3.5,"y":-1},{"x":7.5,"y":-1}]},{"index":1,"tiles":[{"x":4.5,"y":-9},{"x":6.5,"y":-9},{"x":4,"y":-8},{"x":5,"y":-8},{"x":6,"y":-8},{"x":7,"y":-8},{"x":3.5,"y":-7},{"x":4.5,"y":-7},{"x":5.5,"y":-7},{"x":6.5,"y":-7},{"x":7.5,"y":-7},{"x":3,"y":-6},{"x":4,"y":-6},{"x":5,"y":-6},{"x":6,"y":-6},{"x":7,"y":-6},{"x":8,"y":-6},{"x":2.5,"y":-5},{"x":3.5,"y":-5},{"x":4.5,"y":-5},{"x":5.5,"y":-5},{"x":6.5,"y":-5},{"x":7.5,"y":-5},{"x":8.5,"y":-5},{"x":2,"y":-4},{"x":3,"y":-4},{"x":4,"y":-4},{"x":5,"y":-4},{"x":6,"y":-4},{"x":7,"y":-4},{"x":8,"y":-4},{"x":9,"y":-4},{"x":3.5,"y":-3},{"x":7.5,"y":-3},{"x":3.5,"y":-2},{"x":7.5,"y":-2},{"x":3.5,"y":-1},{"x":7.5,"y":-1}]},{"index":2,"tiles":[{"x":4.5,"y":-7},{"x":5.5,"y":-7},{"x":6.5,"y":-7},{"x":4,"y":-6},{"x":5,"y":-6},{"x":6,"y":-6},{"x":7,"y":-6},{"x":3.5,"y":-5},{"x":4.5,"y":-5},{"x":5.5,"y":-5},{"x":6.5,"y":-5},{"x":7.5,"y":-5},{"x":3,"y":-4},{"x":4,"y":-4},{"x":5,"y":-4},{"x":6,"y":-4},{"x":7,"y":-4},{"x":8,"y":-4},{"x":3.5,"y":-3},{"x":7.5,"y":-3},{"x":3.5,"y":-2},{"x":7.5,"y":-2},{"x":3.5,"y":-1},{"x":7.5,"y":-1}]}],"seeds":["HGcQocY5BvGhUrSFilglg6ckzDV4T0GWTDV6YXZgwhdyYUg1YtAtXARy3vFkSDc5IHVhy5ZOomFJiBo05gl2RgF60NdZn6eJEAgK"]},{"layers":[{"index":0,"tiles":[{"x":2.5,"y":-9.5},{"x":8.5,"y":-9.5},{"x":1.5,"y":-9},{"x":5,"y":-9},{"x":6,"y":-9},{"x":9.5,"y":-9},{"x":2.5,"y":-8.5},{"x":3.5,"y":-8.5},{"x":7.5,"y":-8.5},{"x":8.5,"y":-8.5},{"x":5.5,"y":-8},{"x":3.5,"y":-7.5},{"x":7.5,"y":-7.5},{"x":3.5,"y":-6.5},{"x":4.5,"y":-6.5},{"x":5.5,"y":-6.5},{"x":6.5,"y":-6.5},{"x":7.5,"y":-6.5},{"x":2.5,"y":-6},{"x":8.5,"y":-6},{"x":3.5,"y":-5.5},{"x":5.5,"y":-5.5},{"x":7.5,"y":-5.5},{"x":2.5,"y":-5},{"x":8.5,"y":-5},{"x":3.5,"y":-4.5},{"x":7.5,"y":-4.5},{"x":2,"y":-4},{"x":9,"y":-4},{"x":3.5,"y":-3.5},{"x":4.5,"y":-3.5},{"x":5.5,"y":-3.5},{"x":6.5,"y":-3.5},{"x":7.5,"y":-3.5},{"x":4.5,"y":-2.5},{"x":6.5,"y":-2.5},{"x":2.5,"y":-2},{"x":8.5,"y":-2},{"x":1.5,"y":-1.5},{"x":5.5,"y":-1.5},{"x":9.5,"y":-1.5},{"x":2.5,"y":-1},{"x":3.5,"y":-1},{"x":4.5,"y":-1},{"x":6.5,"y":-1},{"x":7.5,"y":-1},{"x":8.5,"y":-1},{"x":5.5,"y":-0.5}]},{"index":1,"tiles":[{"x":2.5,"y":-9.5},{"x":8.5,"y":-9.5},{"x":1.5,"y":-9},{"x":5,"y":-9},{"x":6,"y":-9},{"x":9.5,"y":-9},{"x":2.5,"y":-8.5},{"x":3.5,"y":-8.5},{"x":7.5,"y":-8.5},{"x":8.5,"y":-8.5},{"x":5.5,"y":-8},{"x":3.5,"y":-7.5},{"x":7.5,"y":-7.5},{"x":3.5,"y":-6.5},{"x":4.5,"y":-6.5},{"x":5.5,"y":-6.5},{"x":6.5,"y":-6.5},{"x":7.5,"y":-6.5},{"x":2.5,"y":-6},{"x":8.5,"y":-6},{"x":3.5,"y":-5.5},{"x":5.5,"y":-5.5},{"x":7.5,"y":-5.5},{"x":2.5,"y":-5},{"x":8.5,"y":-5},{"x":3.5,"y":-4.5},{"x":7.5,"y":-4.5},{"x":2,"y":-4},{"x":9,"y":-4},{"x":3.5,"y":-3.5},{"x":4.5,"y":-3.5},{"x":5.5,"y":-3.5},{"x":6.5,"y":-3.5},{"x":7.5,"y":-3.5},{"x":4.5,"y":-2.5},{"x":6.5,"y":-2.5},{"x":2.5,"y":-2},{"x":8.5,"y":-2},{"x":1.5,"y":-1.5},{"x":5.5,"y":-1.5},{"x":9.5,"y":-1.5},{"x":2.5,"y":-1},{"x":3.5,"y":-1},{"x":4.5,"y":-1},{"x":6.5,"y":-1},{"x":7.5,"y":-1},{"x":8.5,"y":-1},{"x":5.5,"y":-0.5}]},{"index":2,"tiles":[{"x":2.5,"y":-9.5},{"x":8.5,"y":-9.5},{"x":1.5,"y":-9},{"x":5,"y":-9},{"x":6,"y":-9},{"x":9.5,"y":-9},{"x":2.5,"y":-8.5},{"x":3.5,"y":-8.5},{"x":7.5,"y":-8.5},{"x":8.5,"y":-8.5},{"x":5.5,"y":-8},{"x":3.5,"y":-7.5},{"x":7.5,"y":-7.5},{"x":3.5,"y":-6.5},{"x":4.5,"y":-6.5},{"x":5.5,"y":-6.5},{"x":6.5,"y":-6.5},{"x":7.5,"y":-6.5},{"x":2.5,"y":-6},{"x":8.5,"y":-6},{"x":3.5,"y":-5.5},{"x":5.5,"y":-5.5},{"x":7.5,"y":-5.5},{"x":2.5,"y":-5},{"x":8.5,"y":-5},{"x":3.5,"y":-4.5},{"x":7.5,"y":-4.5},{"x":2,"y":-4},{"x":9,"y":-4},{"x":3.5,"y":-3.5},{"x":4.5,"y":-3.5},{"x":5.5,"y":-3.5},{"x":6.5,"y":-3.5},{"x":7.5,"y":-3.5}]}],"seeds":["3DAYQac0W7Mp3GCWnqhpZ2KIoFVMXjKKl/QoE1JlnHNgoBJ2xQJGX0dVAhVQgRhSR9iBxCSBS8h95Ed14rIgF8EoVNiBCBOCSBeGHBpEqkdNEzYQBOh4VKdMYppZAvR8EAcA"]},{"layers":[{"index":0,"tiles":[{"x":3.5,"y":-9},{"x":5.5,"y":-9},{"x":7.5,"y":-9},{"x":2.5,"y":-8.5},{"x":4.5,"y":-8.5},{"x":6.5,"y":-8.5},{"x":8.5,"y":-8.5},{"x":3.5,"y":-8},{"x":5.5,"y":-8},{"x":7.5,"y":-8},{"x":5.5,"y":-7},{"x":5.5,"y":-6},{"x":1.5,"y":-5},{"x":5,"y":-5},{"x":6,"y":-5},{"x":9.5,"y":-5},{"x":1.5,"y":-4},{"x":4,"y":-4},{"x":5,"y":-4},{"x":6,"y":-4},{"x":7,"y":-4},{"x":9.5,"y":-4},{"x":1.5,"y":-3},{"x":3,"y":-3},{"x":4,"y":-3},{"x":7,"y":-3},{"x":8,"y":-3},{"x":9.5,"y":-3},{"x":1.5,"y":-2},{"x":2.5,"y":-2},{"x":3.5,"y":-2},{"x":4.5,"y":-2},{"x":5.5,"y":-2},{"x":6.5,"y":-2},{"x":7.5,"y":-2},{"x":8.5,"y":-2},{"x":9.5,"y":-2}]},{"index":1,"tiles":[{"x":3.5,"y":-9},{"x":5.5,"y":-9},{"x":7.5,"y":-9},{"x":2.5,"y":-8.5},{"x":4.5,"y":-8.5},{"x":6.5,"y":-8.5},{"x":8.5,"y":-8.5},{"x":3.5,"y":-8},{"x":5.5,"y":-8},{"x":7.5,"y":-8},{"x":5.5,"y":-7},{"x":5.5,"y":-6},{"x":1.5,"y":-5},{"x":5,"y":-5},{"x":6,"y":-5},{"x":9.5,"y":-5},{"x":1.5,"y":-4},{"x":4,"y":-4},{"x":5,"y":-4},{"x":6,"y":-4},{"x":7,"y":-4},{"x":9.5,"y":-4},{"x":1.5,"y":-3},{"x":3,"y":-3},{"x":4,"y":-3},{"x":7,"y":-3},{"x":8,"y":-3},{"x":9.5,"y":-3},{"x":1.5,"y":-2},{"x":2.5,"y":-2},{"x":3.5,"y":-2},{"x":4.5,"y":-2},{"x":5.5,"y":-2},{"x":6.5,"y":-2},{"x":7.5,"y":-2},{"x":8.5,"y":-2},{"x":9.5,"y":-2}]},{"index":2,"tiles":[{"x":3.5,"y":-9},{"x":5.5,"y":-9},{"x":7.5,"y":-9},{"x":2.5,"y":-8.5},{"x":4.5,"y":-8.5},{"x":6.5,"y":-8.5},{"x":8.5,"y":-8.5},{"x":3.5,"y":-8},{"x":5.5,"y":-8},{"x":7.5,"y":-8},{"x":5.5,"y":-7},{"x":5.5,"y":-6},{"x":1.5,"y":-5},{"x":5,"y":-5},{"x":6,"y":-5},{"x":9.5,"y":-5},{"x":1.5,"y":-4},{"x":4,"y":-4},{"x":5,"y":-4},{"x":6,"y":-4},{"x":7,"y":-4},{"x":9.5,"y":-4},{"x":1.5,"y":-3},{"x":3,"y":-3},{"x":4,"y":-3},{"x":7,"y":-3},{"x":8,"y":-3},{"x":9.5,"y":-3},{"x":1.5,"y":-2},{"x":2.5,"y":-2},{"x":3.5,"y":-2},{"x":4.5,"y":-2},{"x":5.5,"y":-2},{"x":6.5,"y":-2},{"x":7.5,"y":-2},{"x":8.5,"y":-2},{"x":9.5,"y":-2}]},{"index":3,"tiles":[{"x":3.5,"y":-9},{"x":5.5,"y":-9},{"x":7.5,"y":-9},{"x":2.5,"y":-8.5},{"x":4.5,"y":-8.5},{"x":6.5,"y":-8.5},{"x":8.5,"y":-8.5},{"x":3.5,"y":-8},{"x":5.5,"y":-8},{"x":7.5,"y":-8},{"x":5.5,"y":-7},{"x":5.5,"y":-6},{"x":1.5,"y":-5},{"x":5,"y":-5},{"x":6,"y":-5},{"x":9.5,"y":-5},{"x":1.5,"y":-4},{"x":4,"y":-4},{"x":5,"y":-4},{"x":6,"y":-4},{"x":7,"y":-4},{"x":9.5,"y":-4},{"x":1.5,"y":-3},{"x":3,"y":-3},{"x":4,"y":-3},{"x":7,"y":-3},{"x":8,"y":-3},{"x":9.5,"y":-3},{"x":1.5,"y":-2},{"x":2.5,"y":-2},{"x":3.5,"y":-2},{"x":4.5,"y":-2},{"x":5.5,"y":-2},{"x":6.5,"y":-2},{"x":7.5,"y":-2},{"x":8.5,"y":-2},{"x":9.5,"y":-2}]}],"seeds":["m1V54hIc4eV9C7d0V2KIgihiDoidiod+omVMHQd24eAlnoKYIaJ1zhCKY8RYH8F9UgeRDncI4rUIYUddE8gUYQGCFdc9oaQU6sZ0TkNNzRcxgwV6JQFyGfeBARWAqQZyAlRUFUGAUzA0VNaIoBI+"]},{"layers":[{"index":0,"tiles":[{"x":1.5,"y":-9},{"x":9.5,"y":-9},{"x":2.5,"y":-8.5},{"x":3.5,"y":-8.5},{"x":4.5,"y":-8.5},{"x":5.5,"y":-8.5},{"x":6.5,"y":-8.5},{"x":7.5,"y":-8.5},{"x":8.5,"y":-8.5},{"x":1.5,"y":-8},{"x":9.5,"y":-8},{"x":2.5,"y":-7.5},{"x":3.5,"y":-7.5},{"x":7.5,"y":-7.5},{"x":8.5,"y":-7.5},{"x":1.5,"y":-7},{"x":9.5,"y":-7},{"x":2.5,"y":-6.5},{"x":3.5,"y":-6.5},{"x":4.5,"y":-6.5},{"x":6.5,"y":-6.5},{"x":7.5,"y":-6.5},{"x":8.5,"y":-6.5},{"x":1.5,"y":-6},{"x":9.5,"y":-6},{"x":2.5,"y":-5.5},{"x":3.5,"y":-5.5},{"x":4.5,"y":-5.5},{"x":6.5,"y":-5.5},{"x":7.5,"y":-5.5},{"x":8.5,"y":-5.5},{"x":1.5,"y":-5},{"x":9.5,"y":-5},{"x":2.5,"y":-4.5},{"x":8.5,"y":-4.5},{"x":1.5,"y":-4},{"x":3.5,"y":-4},{"x":7.5,"y":-4},{"x":9.5,"y":-4},{"x":2.5,"y":-3.5},{"x":8.5,"y":-3.5},{"x":1.5,"y":-3},{"x":3.5,"y":-3},{"x":4.5,"y":-3},{"x":6.5,"y":-3},{"x":7.5,"y":-3},{"x":9.5,"y":-3},{"x":2.5,"y":-2.5},{"x":8.5,"y":-2.5},{"x":1.5,"y":-2},{"x":3.5,"y":-2},{"x":7.5,"y":-2},{"x":9.5,"y":-2},{"x":2.5,"y":-1.5},{"x":8.5,"y":-1.5},{"x":3.5,"y":-1},{"x":7.5,"y":-1}]},{"index":1,"tiles":[{"x":1.5,"y":-9},{"x":9.5,"y":-9},{"x":2.5,"y":-8.5},{"x":3.5,"y":-8.5},{"x":4.5,"y":-8.5},{"x":5.5,"y":-8.5},{"x":6.5,"y":-8.5},{"x":7.5,"y":-8.5},{"x":8.5,"y":-8.5},{"x":1.5,"y":-8},{"x":9.5,"y":-8},{"x":2.5,"y":-7.5},{"x":3.5,"y":-7.5},{"x":7.5,"y":-7.5},{"x":8.5,"y":-7.5},{"x":1.5,"y":-7},{"x":9.5,"y":-7},{"x":2.5,"y":-6.5},{"x":3.5,"y":-6.5},{"x":4.5,"y":-6.5},{"x":6.5,"y":-6.5},{"x":7.5,"y":-6.5},{"x":8.5,"y":-6.5},{"x":1.5,"y":-6},{"x":9.5,"y":-6},{"x":2.5,"y":-5.5},{"x":3.5,"y":-5.5},{"x":4.5,"y":-5.5},{"x":6.5,"y":-5.5},{"x":7.5,"y":-5.5},{"x":8.5,"y":-5.5},{"x":1.5,"y":-5},{"x":9.5,"y":-5},{"x":2.5,"y":-4.5},{"x":8.5,"y":-4.5},{"x":1.5,"y":-4},{"x":3.5,"y":-4},{"x":7.5,"y":-4},{"x":9.5,"y":-4},{"x":2.5,"y":-3.5},{"x":8.5,"y":-3.5},{"x":1.5,"y":-3},{"x":3.5,"y":-3},{"x":4.5,"y":-3},{"x":6.5,"y":-3},{"x":7.5,"y":-3},{"x":9.5,"y":-3},{"x":2.5,"y":-2.5},{"x":8.5,"y":-2.5},{"x":1.5,"y":-2},{"x":3.5,"y":-2},{"x":7.5,"y":-2},{"x":9.5,"y":-2},{"x":2.5,"y":-1.5},{"x":8.5,"y":-1.5},{"x":3.5,"y":-1},{"x":7.5,"y":-1}]},{"index":2,"tiles":[{"x":3.5,"y":-3},{"x":4.5,"y":-3},{"x":6.5,"y":-3},{"x":7.5,"y":-3},{"x":3.5,"y":-2},{"x":7.5,"y":-2},{"x":3.5,"y":-1},{"x":7.5,"y":-1}]}],"seeds":["oLdNpqKgR0hYauAxWMgoHod0XAASg1iIQpc2UtRln9CFzzI0WOSEnigmIXRNHsWF03JNHEhRH3eMoLIY5GCBySIIklZl31OKIhcYnYYE4QeGlHNCG1MNDFh0oAcA"]},{"layers":[{"index":0,"tiles":[{"x":3,"y":-8.5},{"x":5.5,"y":-8.5},{"x":8,"y":-8.5},{"x":4.5,"y":-7.5},{"x":6.5,"y":-7.5},{"x":2.5,"y":-7},{"x":3.5,"y":-7},{"x":7.5,"y":-7},{"x":8.5,"y":-7},{"x":1.5,"y":-6.5},{"x":4.5,"y":-6.5},{"x":6.5,"y":-6.5},{"x":9.5,"y":-6.5},{"x":2.5,"y":-6},{"x":8.5,"y":-6},{"x":3.5,"y":-5.5},{"x":4.5,"y":-5.5},{"x":5.5,"y":-5.5},{"x":6.5,"y":-5.5},{"x":7.5,"y":-5.5},{"x":1.5,"y":-5},{"x":9.5,"y":-5},{"x":3.5,"y":-4.5},{"x":4.5,"y":-4.5},{"x":5.5,"y":-4.5},{"x":6.5,"y":-4.5},{"x":7.5,"y":-4.5},{"x":2.5,"y":-4},{"x":8.5,"y":-4},{"x":1.5,"y":-3.5},{"x":4.5,"y":-3.5},{"x":6.5,"y":-3.5},{"x":9.5,"y":-3.5},{"x":2.5,"y":-3},{"x":3.5,"y":-3},{"x":7.5,"y":-3},{"x":8.5,"y":-3},{"x":4.5,"y":-2.5},{"x":6.5,"y":-2.5},{"x":3,"y":-1.5},{"x":5.5,"y":-1.5},{"x":8,"y":-1.5}]},{"index":1,"tiles":[{"x":3,"y":-8.5},{"x":5.5,"y":-8.5},{"x":8,"y":-8.5},{"x":4.5,"y":-7},{"x":6.5,"y":-7},{"x":1.5,"y":-6.5},{"x":3.5,"y":-6.5},{"x":7.5,"y":-6.5},{"x":9.5,"y":-6.5},{"x":2.5,"y":-6},{"x":4.5,"y":-6},{"x":6.5,"y":-6},{"x":8.5,"y":-6},{"x":3.5,"y":-5.5},{"x":7.5,"y":-5.5},{"x":1.5,"y":-5},{"x":5,"y":-5},{"x":6,"y":-5},{"x":9.5,"y":-5},{"x":3.5,"y":-4.5},{"x":7.5,"y":-4.5},{"x":2.5,"y":-4},{"x":4.5,"y":-4},{"x":6.5,"y":-4},{"x":8.5,"y":-4},{"x":1.5,"y":-3.5},{"x":3.5,"y":-3.5},{"x":7.5,"y":-3.5},{"x":9.5,"y":-3.5},{"x":4.5,"y":-3},{"x":6.5,"y":-3},{"x":3,"y":-1.5},{"x":5.5,"y":-1.5},{"x":8,"y":-1.5}]},{"index":2,"tiles":[{"x":5.5,"y":-8},{"x":3.5,"y":-6.5},{"x":7.5,"y":-6.5},{"x":2.5,"y":-6},{"x":4.5,"y":-6},{"x":6.5,"y":-6},{"x":8.5,"y":-6},{"x":2,"y":-5},{"x":3,"y":-5},{"x":4,"y":-5},{"x":5,"y":-5},{"x":6,"y":-5},{"x":7,"y":-5},{"x":8,"y":-5},{"x":9,"y":-5},{"x":2.5,"y":-4},{"x":4.5,"y":-4},{"x":6.5,"y":-4},{"x":8.5,"y":-4},{"x":3.5,"y":-3.5},{"x":7.5,"y":-3.5},{"x":5.5,"y":-2}]}],"seeds":["ltIlImiiAXOp4xYined0y0CEQxUIW8MlwfeBxiF8WRdNX0oVU2hxR0kgDshBkCaGy3NJAaiEXgWGEsVwnMeBD3limhhhRSYajQcA"]},{"layers":[{"index":0,"tiles":[{"x":9.5,"y":-10},{"x":2,"y":-9.5},{"x":8.5,"y":-9.5},{"x":3,"y":-9},{"x":5,"y":-9},{"x":8,"y":-8.5},{"x":3.5,"y":-8},{"x":5.5,"y":-8},{"x":7.5,"y":-7.5},{"x":9.5,"y":-7.5},{"x":4,"y":-7},{"x":6,"y":-7},{"x":3,"y":-6.5},{"x":5,"y":-6.5},{"x":7,"y":-6.5},{"x":9,"y":-6.5},{"x":2.5,"y":-5.5},{"x":4.5,"y":-5.5},{"x":6.5,"y":-5.5},{"x":8.5,"y":-5.5},{"x":2,"y":-4.5},{"x":4,"y":-4.5},{"x":6,"y":-4.5},{"x":8,"y":-4.5},{"x":5,"y":-4},{"x":7,"y":-4},{"x":1.5,"y":-3.5},{"x":3.5,"y":-3.5},{"x":5.5,"y":-3},{"x":7.5,"y":-3},{"x":3,"y":-2.5},{"x":6,"y":-2},{"x":8,"y":-2},{"x":2.5,"y":-1.5},{"x":9,"y":-1.5},{"x":1.5,"y":-1}]},{"index":1,"tiles":[{"x":9.5,"y":-10},{"x":2,"y":-9.5},{"x":8.5,"y":-9.5},{"x":3,"y":-9},{"x":5,"y":-9},{"x":8,"y":-8.5},{"x":3.5,"y":-8},{"x":5.5,"y":-8},{"x":7.5,"y":-7.5},{"x":9.5,"y":-7.5},{"x":4,"y":-7},{"x":6,"y":-7},{"x":3,"y":-6.5},{"x":5,"y":-6.5},{"x":7,"y":-6.5},{"x":9,"y":-6.5},{"x":2.5,"y":-5.5},{"x":4.5,"y":-5.5},{"x":6.5,"y":-5.5},{"x":8.5,"y":-5.5},{"x":2,"y":-4.5},{"x":4,"y":-4.5},{"x":6,"y":-4.5},{"x":8,"y":-4.5},{"x":5,"y":-4},{"x":7,"y":-4},{"x":1.5,"y":-3.5},{"x":3.5,"y":-3.5},{"x":5.5,"y":-3},{"x":7.5,"y":-3},{"x":3,"y":-2.5},{"x":6,"y":-2},{"x":8,"y":-2},{"x":2.5,"y":-1.5},{"x":9,"y":-1.5},{"x":1.5,"y":-1}]}],"seeds":["HliIxyieASgq4TeRA9RhhgkGqXAJxPVwnAExVvM9YTWF4mI1YFeExOI4DDdgKEdVnaeWHaUc"]},{"layers":[{"index":0,"tiles":[{"x":4.5,"y":-9.5},{"x":3.5,"y":-9},{"x":5.5,"y":-9},{"x":2.5,"y":-8.5},{"x":4.5,"y":-8.5},{"x":6.5,"y":-8.5},{"x":3.5,"y":-8},{"x":5.5,"y":-8},{"x":7.5,"y":-8},{"x":2.5,"y":-7.5},{"x":4.5,"y":-7.5},{"x":6.5,"y":-7.5},{"x":3.5,"y":-7},{"x":5.5,"y":-7},{"x":7.5,"y":-7},{"x":4.5,"y":-6.5},{"x":6.5,"y":-6.5},{"x":8.5,"y":-6.5},{"x":3.5,"y":-6},{"x":5.5,"y":-6},{"x":7.5,"y":-6},{"x":2.5,"y":-5.5},{"x":4.5,"y":-5.5},{"x":6.5,"y":-5.5},{"x":8.5,"y":-5.5},{"x":3.5,"y":-5},{"x":5.5,"y":-5},{"x":7.5,"y":-5},{"x":2.5,"y":-4.5},{"x":4.5,"y":-4.5},{"x":6.5,"y":-4.5},{"x":8.5,"y":-4.5},{"x":3.5,"y":-4},{"x":5.5,"y":-4},{"x":7.5,"y":-4},{"x":4.5,"y":-3.5},{"x":6.5,"y":-3.5},{"x":8.5,"y":-3.5},{"x":3.5,"y":-3},{"x":5.5,"y":-3},{"x":7.5,"y":-3},{"x":2.5,"y":-2.5},{"x":4.5,"y":-2.5},{"x":6.5,"y":-2.5},{"x":3.5,"y":-2},{"x":5.5,"y":-2},{"x":7.5,"y":-2},{"x":2.5,"y":-1.5},{"x":4.5,"y":-1.5},{"x":6.5,"y":-1.5},{"x":3.5,"y":-1},{"x":5.5,"y":-1},{"x":4.5,"y":-0.5}]},{"index":1,"tiles":[{"x":3,"y":-8.5},{"x":4,"y":-8.5},{"x":5,"y":-8.5},{"x":6,"y":-8},{"x":3,"y":-7.5},{"x":4,"y":-7.5},{"x":5,"y":-7.5},{"x":7,"y":-7.5},{"x":6,"y":-7},{"x":5,"y":-6.5},{"x":7,"y":-6.5},{"x":6,"y":-6},{"x":8,"y":-6},{"x":5,"y":-5.5},{"x":7,"y":-5.5},{"x":3,"y":-5},{"x":4,"y":-5},{"x":6,"y":-5},{"x":8,"y":-5},{"x":5,"y":-4.5},{"x":7,"y":-4.5},{"x":6,"y":-4},{"x":8,"y":-4},{"x":5,"y":-3.5},{"x":7,"y":-3.5},{"x":6,"y":-3},{"x":3,"y":-2.5},{"x":4,"y":-2.5},{"x":5,"y":-2.5},{"x":7,"y":-2.5},{"x":6,"y":-2},{"x":3,"y":-1.5},{"x":4,"y":-1.5},{"x":5,"y":-1.5}]},{"index":2,"tiles":[{"x":3.5,"y":-8.5},{"x":4.5,"y":-8.5},{"x":3.5,"y":-7.5},{"x":4.5,"y":-7.5},{"x":5.5,"y":-7.5},{"x":6.5,"y":-7},{"x":5.5,"y":-6.5},{"x":6.5,"y":-6},{"x":5.5,"y":-5.5},{"x":7.5,"y":-5.5},{"x":3.5,"y":-5},{"x":4.5,"y":-5},{"x":6.5,"y":-5},{"x":5.5,"y":-4.5},{"x":7.5,"y":-4.5},{"x":6.5,"y":-4},{"x":5.5,"y":-3.5},{"x":6.5,"y":-3},{"x":3.5,"y":-2.5},{"x":4.5,"y":-2.5},{"x":5.5,"y":-2.5},{"x":3.5,"y":-1.5},{"x":4.5,"y":-1.5}]},{"index":3,"tiles":[{"x":4,"y":-8},{"x":6,"y":-6.5},{"x":6,"y":-5.5},{"x":4,"y":-5},{"x":5,"y":-5},{"x":7,"y":-5},{"x":6,"y":-4.5},{"x":6,"y":-3.5},{"x":4,"y":-2}]},{"index":4,"tiles":[{"x":6,"y":-6},{"x":4.5,"y":-5},{"x":5.5,"y":-5},{"x":6.5,"y":-5},{"x":6,"y":-4}]},{"index":5,"tiles":[{"x":6,"y":-5.5},{"x":5,"y":-5},{"x":6,"y":-4.5}]},{"index":6,"tiles":[{"x":5.5,"y":-5}]}],"seeds":["wiASYjd16Ud0IMk5U+dslgBJhSc2j/E8SqCAIChyRnFyD6WIVmUJXrKFn1de2EVRVwReSJUJmoclS0BFE6cU4YFyRUchYdMth2pqSydyXTCFUNeBYMh8jLV8IwWGmRQM"]},{"layers":[{"index":0,"tiles":[{"x":3.5,"y":-8},{"x":7.5,"y":-8},{"x":2.5,"y":-7.5},{"x":4.5,"y":-7.5},{"x":6.5,"y":-7.5},{"x":8.5,"y":-7.5},{"x":1.5,"y":-7},{"x":3.5,"y":-7},{"x":5.5,"y":-7},{"x":7.5,"y":-7},{"x":9.5,"y":-7},{"x":2.5,"y":-6.5},{"x":4.5,"y":-6.5},{"x":6.5,"y":-6.5},{"x":8.5,"y":-6.5},{"x":1.5,"y":-6},{"x":3.5,"y":-6},{"x":5.5,"y":-6},{"x":7.5,"y":-6},{"x":9.5,"y":-6},{"x":2.5,"y":-5.5},{"x":4.5,"y":-5.5},{"x":6.5,"y":-5.5},{"x":8.5,"y":-5.5},{"x":2.5,"y":-4.5},{"x":4.5,"y":-4.5},{"x":6.5,"y":-4.5},{"x":8.5,"y":-4.5},{"x":1.5,"y":-4},{"x":3.5,"y":-4},{"x":5.5,"y":-4},{"x":7.5,"y":-4},{"x":9.5,"y":-4},{"x":2.5,"y":-3.5},{"x":4.5,"y":-3.5},{"x":6.5,"y":-3.5},{"x":8.5,"y":-3.5},{"x":1.5,"y":-3},{"x":3.5,"y":-3},{"x":5.5,"y":-3},{"x":7.5,"y":-3},{"x":9.5,"y":-3},{"x":2.5,"y":-2.5},{"x":4.5,"y":-2.5},{"x":6.5,"y":-2.5},{"x":8.5,"y":-2.5},{"x":3.5,"y":-2},{"x":7.5,"y":-2}]},{"index":1,"tiles":[{"x":3.5,"y":-8},{"x":7.5,"y":-8},{"x":2.5,"y":-7.5},{"x":4.5,"y":-7.5},{"x":6.5,"y":-7.5},{"x":8.5,"y":-7.5},{"x":1.5,"y":-7},{"x":3.5,"y":-7},{"x":5.5,"y":-7},{"x":7.5,"y":-7},{"x":9.5,"y":-7},{"x":2.5,"y":-6.5},{"x":4.5,"y":-6.5},{"x":6.5,"y":-6.5},{"x":8.5,"y":-6.5},{"x":1.5,"y":-6},{"x":3.5,"y":-6},{"x":5.5,"y":-6},{"x":7.5,"y":-6},{"x":9.5,"y":-6},{"x":2.5,"y":-5.5},{"x":4.5,"y":-5.5},{"x":6.5,"y":-5.5},{"x":8.5,"y":-5.5},{"x":2.5,"y":-4.5},{"x":4.5,"y":-4.5},{"x":6.5,"y":-4.5},{"x":8.5,"y":-4.5},{"x":1.5,"y":-4},{"x":3.5,"y":-4},{"x":5.5,"y":-4},{"x":7.5,"y":-4},{"x":9.5,"y":-4},{"x":2.5,"y":-3.5},{"x":4.5,"y":-3.5},{"x":6.5,"y":-3.5},{"x":8.5,"y":-3.5},{"x":1.5,"y":-3},{"x":3.5,"y":-3},{"x":5.5,"y":-3},{"x":7.5,"y":-3},{"x":9.5,"y":-3},{"x":2.5,"y":-2.5},{"x":4.5,"y":-2.5},{"x":6.5,"y":-2.5},{"x":8.5,"y":-2.5},{"x":3.5,"y":-2},{"x":7.5,"y":-2}]},{"index":2,"tiles":[{"x":3.5,"y":-8},{"x":7.5,"y":-8},{"x":4.5,"y":-7.5},{"x":6.5,"y":-7.5},{"x":3.5,"y":-7},{"x":5.5,"y":-7},{"x":7.5,"y":-7},{"x":4.5,"y":-6.5},{"x":6.5,"y":-6.5},{"x":3.5,"y":-6},{"x":5.5,"y":-6},{"x":7.5,"y":-6},{"x":4.5,"y":-5.5},{"x":6.5,"y":-5.5},{"x":4.5,"y":-4.5},{"x":6.5,"y":-4.5},{"x":3.5,"y":-4},{"x":5.5,"y":-4},{"x":7.5,"y":-4},{"x":4.5,"y":-3.5},{"x":6.5,"y":-3.5},{"x":3.5,"y":-3},{"x":5.5,"y":-3},{"x":7.5,"y":-3},{"x":4.5,"y":-2.5},{"x":6.5,"y":-2.5},{"x":3.5,"y":-2},{"x":7.5,"y":-2}]},{"index":3,"tiles":[{"x":5.5,"y":-7},{"x":5.5,"y":-6},{"x":5.5,"y":-4},{"x":5.5,"y":-3}]}],"seeds":["GKV2AnZRH9gFTjdGi/JonONl3pZw0XaUTIJZIslZmfSFqBd4k7aAHTd0AQhKhxBCIkhVBtg41DcxwqN4FQcixtAg3klMYOcs3tWFXUoVYhhAoFKIoacQwmRin0iJIQcu"]},{"layers":[{"index":0,"tiles":[{"x":4.5,"y":-8},{"x":6.5,"y":-8},{"x":2.5,"y":-7.5},{"x":3.5,"y":-7.5},{"x":5.5,"y":-7.5},{"x":7.5,"y":-7.5},{"x":8.5,"y":-7.5},{"x":4.5,"y":-7},{"x":6.5,"y":-7},{"x":1.5,"y":-6.5},{"x":3.5,"y":-6.5},{"x":7.5,"y":-6.5},{"x":9.5,"y":-6.5},{"x":4.5,"y":-6},{"x":6.5,"y":-6},{"x":1.5,"y":-5.5},{"x":9.5,"y":-5.5},{"x":0.5,"y":-5},{"x":4.5,"y":-5},{"x":6.5,"y":-5},{"x":10.5,"y":-5},{"x":1.5,"y":-4.5},{"x":2.5,"y":-4.5},{"x":3.5,"y":-4.5},{"x":5.5,"y":-4.5},{"x":7.5,"y":-4.5},{"x":8.5,"y":-4.5},{"x":9.5,"y":-4.5},{"x":1.5,"y":-3.5},{"x":2.5,"y":-3.5},{"x":3.5,"y":-3.5},{"x":5.5,"y":-3.5},{"x":7.5,"y":-3.5},{"x":8.5,"y":-3.5},{"x":9.5,"y":-3.5},{"x":0.5,"y":-3},{"x":4.5,"y":-3},{"x":6.5,"y":-3},{"x":10.5,"y":-3},{"x":1.5,"y":-2.5},{"x":9.5,"y":-2.5},{"x":4.5,"y":-2},{"x":6.5,"y":-2},{"x":1.5,"y":-1.5},{"x":3.5,"y":-1.5},{"x":7.5,"y":-1.5},{"x":9.5,"y":-1.5},{"x":4.5,"y":-1},{"x":6.5,"y":-1},{"x":2.5,"y":-0.5},{"x":3.5,"y":-0.5},{"x":5.5,"y":-0.5},{"x":7.5,"y":-0.5},{"x":8.5,"y":-0.5},{"x":4.5,"y":0},{"x":6.5,"y":0}]},{"index":1,"tiles":[{"x":4.5,"y":-8},{"x":6.5,"y":-8},{"x":2.5,"y":-7.5},{"x":3.5,"y":-7.5},{"x":5.5,"y":-7.5},{"x":7.5,"y":-7.5},{"x":8.5,"y":-7.5},{"x":4.5,"y":-7},{"x":6.5,"y":-7},{"x":1.5,"y":-6.5},{"x":3.5,"y":-6.5},{"x":7.5,"y":-6.5},{"x":9.5,"y":-6.5},{"x":4.5,"y":-6},{"x":6.5,"y":-6},{"x":1.5,"y":-5.5},{"x":9.5,"y":-5.5},{"x":0.5,"y":-5},{"x":4.5,"y":-5},{"x":6.5,"y":-5},{"x":10.5,"y":-5},{"x":1.5,"y":-4.5},{"x":2.5,"y":-4.5},{"x":3.5,"y":-4.5},{"x":5.5,"y":-4.5},{"x":7.5,"y":-4.5},{"x":8.5,"y":-4.5},{"x":9.5,"y":-4.5},{"x":1.5,"y":-3.5},{"x":2.5,"y":-3.5},{"x":3.5,"y":-3.5},{"x":5.5,"y":-3.5},{"x":7.5,"y":-3.5},{"x":8.5,"y":-3.5},{"x":9.5,"y":-3.5},{"x":0.5,"y":-3},{"x":4.5,"y":-3},{"x":6.5,"y":-3},{"x":10.5,"y":-3},{"x":1.5,"y":-2.5},{"x":9.5,"y":-2.5},{"x":4.5,"y":-2},{"x":6.5,"y":-2},{"x":1.5,"y":-1.5},{"x":3.5,"y":-1.5},{"x":7.5,"y":-1.5},{"x":9.5,"y":-1.5},{"x":4.5,"y":-1},{"x":6.5,"y":-1},{"x":2.5,"y":-0.5},{"x":3.5,"y":-0.5},{"x":5.5,"y":-0.5},{"x":7.5,"y":-0.5},{"x":8.5,"y":-0.5},{"x":4.5,"y":0},{"x":6.5,"y":0}]}],"seeds":["ngOK4BcGwUeKzFNJjHh4SqCC5QYG3AkKD3d9FDeBTad5WDFhw2aKYhgaTQR2EihkXGeJh4Yk15EiEFNFaDGMUKgwHnOEIZSIBMNR1pKJjsF9UEcs"]},{"layers":[{"index":0,"tiles":[{"x":3,"y":-9},{"x":8,"y":-9},{"x":2,"y":-8.5},{"x":4,"y":-8.5},{"x":7,"y":-8.5},{"x":9,"y":-8.5},{"x":3,"y":-8},{"x":5.5,"y":-8},{"x":8,"y":-8},{"x":2,"y":-7.5},{"x":4,"y":-7.5},{"x":7,"y":-7.5},{"x":9,"y":-7.5},{"x":3,"y":-7},{"x":5.5,"y":-7},{"x":8,"y":-7},{"x":2,"y":-6.5},{"x":4,"y":-6.5},{"x":7,"y":-6.5},{"x":9,"y":-6.5},{"x":3,"y":-6},{"x":5.5,"y":-6},{"x":8,"y":-6},{"x":2,"y":-5.5},{"x":4,"y":-5.5},{"x":7,"y":-5.5},{"x":9,"y":-5.5},{"x":3,"y":-5},{"x":5.5,"y":-5},{"x":8,"y":-5},{"x":2,"y":-4.5},{"x":4,"y":-4.5},{"x":7,"y":-4.5},{"x":9,"y":-4.5},{"x":3,"y":-4},{"x":5.5,"y":-4},{"x":8,"y":-4},{"x":2,"y":-3.5},{"x":4,"y":-3.5},{"x":7,"y":-3.5},{"x":9,"y":-3.5},{"x":5.5,"y":-3},{"x":1.5,"y":-2.5},{"x":2.5,"y":-2.5},{"x":3.5,"y":-2.5},{"x":4.5,"y":-2.5},{"x":6.5,"y":-2.5},{"x":7.5,"y":-2.5},{"x":8.5,"y":-2.5},{"x":9.5,"y":-2.5},{"x":5.5,"y":-2},{"x":2,"y":-1.5},{"x":3,"y":-1.5},{"x":8,"y":-1.5},{"x":9,"y":-1.5},{"x":4,"y":-1},{"x":7,"y":-1},{"x":5,"y":-0.5},{"x":6,"y":-0.5}]},{"index":1,"tiles":[{"x":2.5,"y":-8},{"x":3.5,"y":-8},{"x":5.5,"y":-8},{"x":7.5,"y":-8},{"x":8.5,"y":-8},{"x":2.5,"y":-7},{"x":3.5,"y":-7},{"x":5.5,"y":-7},{"x":7.5,"y":-7},{"x":8.5,"y":-7},{"x":2.5,"y":-6},{"x":3.5,"y":-6},{"x":5.5,"y":-6},{"x":7.5,"y":-6},{"x":8.5,"y":-6},{"x":2.5,"y":-5},{"x":3.5,"y":-5},{"x":5.5,"y":-5},{"x":7.5,"y":-5},{"x":8.5,"y":-5},{"x":2.5,"y":-4},{"x":3.5,"y":-4},{"x":5.5,"y":-4},{"x":7.5,"y":-4},{"x":8.5,"y":-4},{"x":5.5,"y":-3},{"x":5.5,"y":-2}]},{"index":2,"tiles":[{"x":3,"y":-7.5},{"x":8,"y":-7.5},{"x":3,"y":-6},{"x":8,"y":-6},{"x":3,"y":-4.5},{"x":8,"y":-4.5}]}],"seeds":["g1F9BwcqFBcGlAd1DpINIJMIVRg8S2F1jiSe0EWCX5otCpocXleqIdEwnDaFocch0/VoghhFINh0ookZ4PiF2Cd6BSFZ"]},{"layers":[{"index":0,"tiles":[{"x":1.5,"y":-7},{"x":2.5,"y":-7},{"x":3.5,"y":-7},{"x":4.5,"y":-7},{"x":5.5,"y":-7},{"x":6.5,"y":-7},{"x":7.5,"y":-7},{"x":8.5,"y":-7},{"x":9.5,"y":-7},{"x":2.5,"y":-6},{"x":3.5,"y":-6},{"x":4.5,"y":-6},{"x":5.5,"y":-6},{"x":6.5,"y":-6},{"x":7.5,"y":-6},{"x":8.5,"y":-6},{"x":1.5,"y":-5.5},{"x":9.5,"y":-5.5},{"x":3.5,"y":-5},{"x":4.5,"y":-5},{"x":5.5,"y":-5},{"x":6.5,"y":-5},{"x":7.5,"y":-5},{"x":3,"y":-4},{"x":4.5,"y":-4},{"x":5.5,"y":-4},{"x":6.5,"y":-4},{"x":8,"y":-4},{"x":5,"y":-3},{"x":6,"y":-3}]},{"index":1,"tiles":[{"x":1.5,"y":-7},{"x":2.5,"y":-7},{"x":3.5,"y":-7},{"x":4.5,"y":-7},{"x":5.5,"y":-7},{"x":6.5,"y":-7},{"x":7.5,"y":-7},{"x":8.5,"y":-7},{"x":9.5,"y":-7},{"x":2.5,"y":-6},{"x":3.5,"y":-6},{"x":4.5,"y":-6},{"x":5.5,"y":-6},{"x":6.5,"y":-6},{"x":7.5,"y":-6},{"x":8.5,"y":-6},{"x":1.5,"y":-5.5},{"x":9.5,"y":-5.5},{"x":3.5,"y":-5},{"x":4.5,"y":-5},{"x":5.5,"y":-5},{"x":6.5,"y":-5},{"x":7.5,"y":-5},{"x":3,"y":-4},{"x":4.5,"y":-4},{"x":5.5,"y":-4},{"x":6.5,"y":-4},{"x":8,"y":-4},{"x":5,"y":-3},{"x":6,"y":-3}]},{"index":2,"tiles":[{"x":1.5,"y":-7},{"x":2.5,"y":-7},{"x":3.5,"y":-7},{"x":4.5,"y":-7},{"x":5.5,"y":-7},{"x":6.5,"y":-7},{"x":7.5,"y":-7},{"x":8.5,"y":-7},{"x":9.5,"y":-7},{"x":2.5,"y":-6},{"x":3.5,"y":-6},{"x":4.5,"y":-6},{"x":5.5,"y":-6},{"x":6.5,"y":-6},{"x":7.5,"y":-6},{"x":8.5,"y":-6},{"x":1.5,"y":-5.5},{"x":9.5,"y":-5.5},{"x":3.5,"y":-5},{"x":4.5,"y":-5},{"x":5.5,"y":-5},{"x":6.5,"y":-5},{"x":7.5,"y":-5},{"x":3,"y":-4},{"x":4.5,"y":-4},{"x":5.5,"y":-4},{"x":6.5,"y":-4},{"x":8,"y":-4},{"x":5,"y":-3},{"x":6,"y":-3}]},{"index":3,"tiles":[{"x":1.5,"y":-7},{"x":2.5,"y":-7},{"x":3.5,"y":-7},{"x":4.5,"y":-7},{"x":5.5,"y":-7},{"x":6.5,"y":-7},{"x":7.5,"y":-7},{"x":8.5,"y":-7},{"x":9.5,"y":-7},{"x":2.5,"y":-6},{"x":3.5,"y":-6},{"x":4.5,"y":-6},{"x":5.5,"y":-6},{"x":6.5,"y":-6},{"x":7.5,"y":-6},{"x":8.5,"y":-6},{"x":1.5,"y":-5.5},{"x":9.5,"y":-5.5},{"x":3.5,"y":-5},{"x":4.5,"y":-5},{"x":5.5,"y":-5},{"x":6.5,"y":-5},{"x":7.5,"y":-5},{"x":3,"y":-4},{"x":4.5,"y":-4},{"x":5.5,"y":-4},{"x":6.5,"y":-4},{"x":8,"y":-4},{"x":5,"y":-3},{"x":6,"y":-3}]}],"seeds":["WDeJw4eB5PZAS3hVBeGFXTY9YJl0nEdxYQdaEbOkHThB0XeEZiYsiaZtgaSMgiEa00IR4SAoQvB5XHAyKCeBlFcFoeKIH0iFYjiIjudxIDJwzaWIBXggVtOp"]},{"layers":[{"index":0,"tiles":[{"x":5.5,"y":-8.5},{"x":4.5,"y":-8},{"x":6.5,"y":-8},{"x":3.5,"y":-7.5},{"x":5.5,"y":-7.5},{"x":7.5,"y":-7.5},{"x":2.5,"y":-7},{"x":4.5,"y":-7},{"x":6.5,"y":-7},{"x":8.5,"y":-7},{"x":3.5,"y":-6.5},{"x":5.5,"y":-6.5},{"x":7.5,"y":-6.5},{"x":2.5,"y":-6},{"x":8.5,"y":-6},{"x":4.5,"y":-5.5},{"x":5.5,"y":-5.5},{"x":6.5,"y":-5.5},{"x":2.5,"y":-5},{"x":3.5,"y":-5},{"x":7.5,"y":-5},{"x":8.5,"y":-5},{"x":4.5,"y":-4.5},{"x":5.5,"y":-4.5},{"x":6.5,"y":-4.5},{"x":2.5,"y":-4},{"x":8.5,"y":-4},{"x":3.5,"y":-3.5},{"x":5.5,"y":-3.5},{"x":7.5,"y":-3.5},{"x":2.5,"y":-3},{"x":4.5,"y":-3},{"x":6.5,"y":-3},{"x":8.5,"y":-3},{"x":3.5,"y":-2.5},{"x":5.5,"y":-2.5},{"x":7.5,"y":-2.5},{"x":4.5,"y":-2},{"x":6.5,"y":-2},{"x":5.5,"y":-1.5}]},{"index":1,"tiles":[{"x":5.5,"y":-8.5},{"x":4.5,"y":-8},{"x":6.5,"y":-8},{"x":3.5,"y":-7.5},{"x":5.5,"y":-7.5},{"x":7.5,"y":-7.5},{"x":2.5,"y":-7},{"x":4.5,"y":-7},{"x":6.5,"y":-7},{"x":8.5,"y":-7},{"x":3.5,"y":-6.5},{"x":5.5,"y":-6.5},{"x":7.5,"y":-6.5},{"x":2.5,"y":-6},{"x":8.5,"y":-6},{"x":4.5,"y":-5.5},{"x":5.5,"y":-5.5},{"x":6.5,"y":-5.5},{"x":2.5,"y":-5},{"x":3.5,"y":-5},{"x":7.5,"y":-5},{"x":8.5,"y":-5},{"x":4.5,"y":-4.5},{"x":5.5,"y":-4.5},{"x":6.5,"y":-4.5},{"x":2.5,"y":-4},{"x":8.5,"y":-4},{"x":3.5,"y":-3.5},{"x":5.5,"y":-3.5},{"x":7.5,"y":-3.5},{"x":2.5,"y":-3},{"x":4.5,"y":-3},{"x":6.5,"y":-3},{"x":8.5,"y":-3},{"x":3.5,"y":-2.5},{"x":5.5,"y":-2.5},{"x":7.5,"y":-2.5},{"x":4.5,"y":-2},{"x":6.5,"y":-2},{"x":5.5,"y":-1.5}]},{"index":2,"tiles":[{"x":5.5,"y":-8.5},{"x":4.5,"y":-8},{"x":6.5,"y":-8},{"x":3.5,"y":-7.5},{"x":5.5,"y":-7.5},{"x":7.5,"y":-7.5},{"x":2.5,"y":-7},{"x":4.5,"y":-7},{"x":6.5,"y":-7},{"x":8.5,"y":-7},{"x":3.5,"y":-6.5},{"x":5.5,"y":-6.5},{"x":7.5,"y":-6.5},{"x":2.5,"y":-6},{"x":4.5,"y":-6},{"x":6.5,"y":-6},{"x":8.5,"y":-6},{"x":3.5,"y":-5.5},{"x":5.5,"y":-5.5},{"x":7.5,"y":-5.5},{"x":2.5,"y":-5},{"x":4.5,"y":-5},{"x":6.5,"y":-5},{"x":8.5,"y":-5},{"x":3.5,"y":-4.5},{"x":5.5,"y":-4.5},{"x":7.5,"y":-4.5},{"x":2.5,"y":-4},{"x":4.5,"y":-4},{"x":6.5,"y":-4},{"x":8.5,"y":-4},{"x":3.5,"y":-3.5},{"x":5.5,"y":-3.5},{"x":7.5,"y":-3.5},{"x":2.5,"y":-3},{"x":4.5,"y":-3},{"x":6.5,"y":-3},{"x":8.5,"y":-3},{"x":3.5,"y":-2.5},{"x":5.5,"y":-2.5},{"x":7.5,"y":-2.5},{"x":4.5,"y":-2},{"x":6.5,"y":-2},{"x":5.5,"y":-1.5}]},{"index":3,"tiles":[{"x":3,"y":-6.5},{"x":8,"y":-6.5},{"x":3,"y":-5.5},{"x":5,"y":-5.5},{"x":6,"y":-5.5},{"x":8,"y":-5.5},{"x":3,"y":-4.5},{"x":4.5,"y":-4.5},{"x":6.5,"y":-4.5},{"x":8,"y":-4.5},{"x":3,"y":-3.5},{"x":4,"y":-3.5},{"x":7,"y":-3.5},{"x":8,"y":-3.5}]}],"seeds":["yedxh2FwWZVAkDh1pxkqjJiG6EdUlGgRhYCASkYqzxA83WRxWxh411IdW8N9l/IRi9chlMCUDbN5ohSEIuiBnIgNBOdZkQBSTAiKzlAsUddIwgg2YTd04PRN4BKK3KdZGhdiTkBV6gYA"]},{"layers":[{"index":0,"tiles":[{"x":4,"y":-9},{"x":5,"y":-9},{"x":6,"y":-9},{"x":7,"y":-9},{"x":3,"y":-8.5},{"x":8,"y":-8.5},{"x":2,"y":-8},{"x":4,"y":-8},{"x":7,"y":-8},{"x":9,"y":-8},{"x":5,"y":-7.5},{"x":6,"y":-7.5},{"x":2,"y":-7},{"x":3,"y":-7},{"x":4,"y":-7},{"x":7,"y":-7},{"x":8,"y":-7},{"x":9,"y":-7},{"x":2,"y":-6},{"x":4,"y":-6},{"x":5,"y":-6},{"x":6,"y":-6},{"x":7,"y":-6},{"x":9,"y":-6},{"x":3,"y":-5.5},{"x":8,"y":-5.5},{"x":2,"y":-5},{"x":4,"y":-5},{"x":5,"y":-5},{"x":6,"y":-5},{"x":7,"y":-5},{"x":9,"y":-5},{"x":3,"y":-4.5},{"x":8,"y":-4.5},{"x":2,"y":-4},{"x":4,"y":-4},{"x":5,"y":-4},{"x":6,"y":-4},{"x":7,"y":-4},{"x":9,"y":-4},{"x":2,"y":-3},{"x":3,"y":-3},{"x":4,"y":-3},{"x":7,"y":-3},{"x":8,"y":-3},{"x":9,"y":-3},{"x":5,"y":-2.5},{"x":6,"y":-2.5},{"x":2,"y":-2},{"x":4,"y":-2},{"x":7,"y":-2},{"x":9,"y":-2},{"x":3,"y":-1.5},{"x":8,"y":-1.5},{"x":4,"y":-1},{"x":5,"y":-1},{"x":6,"y":-1},{"x":7,"y":-1}]},{"index":1,"tiles":[{"x":4,"y":-9},{"x":5,"y":-9},{"x":6,"y":-9},{"x":7,"y":-9},{"x":3,"y":-8.5},{"x":8,"y":-8.5},{"x":2,"y":-8},{"x":4,"y":-8},{"x":7,"y":-8},{"x":9,"y":-8},{"x":5,"y":-7.5},{"x":6,"y":-7.5},{"x":2,"y":-7},{"x":3,"y":-7},{"x":4,"y":-7},{"x":7,"y":-7},{"x":8,"y":-7},{"x":9,"y":-7},{"x":2,"y":-6},{"x":4,"y":-6},{"x":5,"y":-6},{"x":6,"y":-6},{"x":7,"y":-6},{"x":9,"y":-6},{"x":3,"y":-5.5},{"x":8,"y":-5.5},{"x":2,"y":-5},{"x":4,"y":-5},{"x":5,"y":-5},{"x":6,"y":-5},{"x":7,"y":-5},{"x":9,"y":-5},{"x":3,"y":-4.5},{"x":8,"y":-4.5},{"x":2,"y":-4},{"x":4,"y":-4},{"x":5,"y":-4},{"x":6,"y":-4},{"x":7,"y":-4},{"x":9,"y":-4},{"x":2,"y":-3},{"x":3,"y":-3},{"x":4,"y":-3},{"x":7,"y":-3},{"x":8,"y":-3},{"x":9,"y":-3},{"x":5,"y":-2.5},{"x":6,"y":-2.5},{"x":2,"y":-2},{"x":4,"y":-2},{"x":7,"y":-2},{"x":9,"y":-2},{"x":3,"y":-1.5},{"x":8,"y":-1.5},{"x":4,"y":-1},{"x":5,"y":-1},{"x":6,"y":-1},{"x":7,"y":-1}]},{"index":2,"tiles":[{"x":5,"y":-8},{"x":6,"y":-8},{"x":3,"y":-7.5},{"x":8,"y":-7.5},{"x":3,"y":-6.5},{"x":5,"y":-6.5},{"x":6,"y":-6.5},{"x":8,"y":-6.5},{"x":5,"y":-5},{"x":6,"y":-5},{"x":3,"y":-3.5},{"x":5,"y":-3.5},{"x":6,"y":-3.5},{"x":8,"y":-3.5},{"x":3,"y":-2.5},{"x":8,"y":-2.5},{"x":5,"y":-2},{"x":6,"y":-2}]}],"seeds":["SgEqgcBh2Sc1lDWVH3KpUYeCYiGGVwdWIOEEYHpSUQNVVfcsIOeFE1d9S8ANCrNRiSKIk2haIeYQ4RcuEOOFSEgxwsgx2eGB3EBqBCGKiyd04PAlU3h4XcCJofcN4mMY4cZpnQQA"]},{"layers":[{"index":0,"tiles":[{"x":3.5,"y":-8.5},{"x":4.5,"y":-8.5},{"x":5.5,"y":-8.5},{"x":6.5,"y":-8.5},{"x":7.5,"y":-8.5},{"x":3.5,"y":-7.5},{"x":4.5,"y":-7.5},{"x":5.5,"y":-7.5},{"x":6.5,"y":-7.5},{"x":7.5,"y":-7.5},{"x":3.5,"y":-6.5},{"x":4.5,"y":-6.5},{"x":5.5,"y":-6.5},{"x":6.5,"y":-6.5},{"x":7.5,"y":-6.5},{"x":3.5,"y":-5.5},{"x":4.5,"y":-5.5},{"x":5.5,"y":-5.5},{"x":6.5,"y":-5.5},{"x":7.5,"y":-5.5},{"x":1.5,"y":-5},{"x":9.5,"y":-5},{"x":3.5,"y":-4.5},{"x":4.5,"y":-4.5},{"x":5.5,"y":-4.5},{"x":6.5,"y":-4.5},{"x":7.5,"y":-4.5},{"x":3.5,"y":-3.5},{"x":4.5,"y":-3.5},{"x":5.5,"y":-3.5},{"x":6.5,"y":-3.5},{"x":7.5,"y":-3.5},{"x":3.5,"y":-2.5},{"x":4.5,"y":-2.5},{"x":5.5,"y":-2.5},{"x":6.5,"y":-2.5},{"x":7.5,"y":-2.5},{"x":3.5,"y":-1.5},{"x":4.5,"y":-1.5},{"x":5.5,"y":-1.5},{"x":6.5,"y":-1.5},{"x":7.5,"y":-1.5}]},{"index":1,"tiles":[{"x":3.5,"y":-8.5},{"x":4.5,"y":-8.5},{"x":5.5,"y":-8.5},{"x":6.5,"y":-8.5},{"x":7.5,"y":-8.5},{"x":3.5,"y":-7.5},{"x":4.5,"y":-7.5},{"x":5.5,"y":-7.5},{"x":6.5,"y":-7.5},{"x":7.5,"y":-7.5},{"x":3.5,"y":-6.5},{"x":4.5,"y":-6.5},{"x":5.5,"y":-6.5},{"x":6.5,"y":-6.5},{"x":7.5,"y":-6.5},{"x":3.5,"y":-5.5},{"x":4.5,"y":-5.5},{"x":5.5,"y":-5.5},{"x":6.5,"y":-5.5},{"x":7.5,"y":-5.5},{"x":3.5,"y":-4.5},{"x":4.5,"y":-4.5},{"x":5.5,"y":-4.5},{"x":6.5,"y":-4.5},{"x":7.5,"y":-4.5},{"x":3.5,"y":-3.5},{"x":4.5,"y":-3.5},{"x":5.5,"y":-3.5},{"x":6.5,"y":-3.5},{"x":7.5,"y":-3.5},{"x":3.5,"y":-2.5},{"x":4.5,"y":-2.5},{"x":5.5,"y":-2.5},{"x":6.5,"y":-2.5},{"x":7.5,"y":-2.5},{"x":3.5,"y":-1.5},{"x":4.5,"y":-1.5},{"x":5.5,"y":-1.5},{"x":6.5,"y":-1.5},{"x":7.5,"y":-1.5}]},{"index":2,"tiles":[{"x":3.5,"y":-8.5},{"x":4.5,"y":-8.5},{"x":5.5,"y":-8.5},{"x":6.5,"y":-8.5},{"x":7.5,"y":-8.5},{"x":3.5,"y":-7.5},{"x":4.5,"y":-7.5},{"x":5.5,"y":-7.5},{"x":6.5,"y":-7.5},{"x":7.5,"y":-7.5},{"x":3.5,"y":-6.5},{"x":4.5,"y":-6.5},{"x":6.5,"y":-6.5},{"x":7.5,"y":-6.5},{"x":3.5,"y":-5.5},{"x":4.5,"y":-5.5},{"x":6.5,"y":-5.5},{"x":7.5,"y":-5.5},{"x":3.5,"y":-4.5},{"x":4.5,"y":-4.5},{"x":6.5,"y":-4.5},{"x":7.5,"y":-4.5},{"x":3.5,"y":-3.5},{"x":4.5,"y":-3.5},{"x":6.5,"y":-3.5},{"x":7.5,"y":-3.5},{"x":3.5,"y":-2.5},{"x":4.5,"y":-2.5},{"x":5.5,"y":-2.5},{"x":6.5,"y":-2.5},{"x":7.5,"y":-2.5},{"x":3.5,"y":-1.5},{"x":4.5,"y":-1.5},{"x":5.5,"y":-1.5},{"x":6.5,"y":-1.5},{"x":7.5,"y":-1.5}]},{"index":3,"tiles":[{"x":3.5,"y":-8.5},{"x":4.5,"y":-8.5},{"x":5.5,"y":-8.5},{"x":6.5,"y":-8.5},{"x":7.5,"y":-8.5},{"x":3.5,"y":-7.5},{"x":7.5,"y":-7.5},{"x":3.5,"y":-6.5},{"x":7.5,"y":-6.5},{"x":3.5,"y":-5.5},{"x":7.5,"y":-5.5},{"x":3.5,"y":-4.5},{"x":7.5,"y":-4.5},{"x":3.5,"y":-3.5},{"x":7.5,"y":-3.5},{"x":3.5,"y":-2.5},{"x":7.5,"y":-2.5},{"x":3.5,"y":-1.5},{"x":4.5,"y":-1.5},{"x":5.5,"y":-1.5},{"x":6.5,"y":-1.5},{"x":7.5,"y":-1.5}]}],"seeds":["JggNggQeIAo2ICEUquiE1kSAYVV1SeAZXROGYjRhiFhW3OaRXGh11LeBnAiJEzemmcEUYQBWjPVJYfdxFKhwX3NNwtcp50V52AQezaMpHhUiireIS6QNgjNMhLUwXLdkhPhwjOgFQ5B8"]},{"layers":[{"index":0,"tiles":[{"x":1.5,"y":-9},{"x":2.5,"y":-9},{"x":3.5,"y":-9},{"x":5.5,"y":-9},{"x":7.5,"y":-9},{"x":8.5,"y":-9},{"x":9.5,"y":-9},{"x":4.5,"y":-8.5},{"x":6.5,"y":-8.5},{"x":3.5,"y":-8},{"x":5.5,"y":-8},{"x":7.5,"y":-8},{"x":2.5,"y":-7.5},{"x":8.5,"y":-7.5},{"x":1.5,"y":-7},{"x":5.5,"y":-7},{"x":9.5,"y":-7},{"x":5.5,"y":-6},{"x":4.5,"y":-5.5},{"x":6.5,"y":-5.5},{"x":3.5,"y":-5},{"x":5.5,"y":-5},{"x":7.5,"y":-5},{"x":2.5,"y":-4.5},{"x":8.5,"y":-4.5},{"x":5,"y":-4},{"x":6,"y":-4},{"x":2,"y":-3.5},{"x":9,"y":-3.5},{"x":4.5,"y":-3},{"x":6.5,"y":-3},{"x":4,"y":-2},{"x":7,"y":-2}]},{"index":1,"tiles":[{"x":1.5,"y":-9},{"x":2.5,"y":-9},{"x":3.5,"y":-9},{"x":7.5,"y":-9},{"x":8.5,"y":-9},{"x":9.5,"y":-9},{"x":4.5,"y":-8.5},{"x":5.5,"y":-8.5},{"x":6.5,"y":-8.5},{"x":3.5,"y":-8},{"x":7.5,"y":-8},{"x":2.5,"y":-7.5},{"x":8.5,"y":-7.5},{"x":1.5,"y":-7},{"x":5.5,"y":-7},{"x":9.5,"y":-7},{"x":5.5,"y":-6},{"x":4.5,"y":-5.5},{"x":6.5,"y":-5.5},{"x":3.5,"y":-5},{"x":5.5,"y":-5},{"x":7.5,"y":-5},{"x":2.5,"y":-4.5},{"x":8.5,"y":-4.5},{"x":5,"y":-4},{"x":6,"y":-4},{"x":2,"y":-3.5},{"x":9,"y":-3.5},{"x":4.5,"y":-3},{"x":6.5,"y":-3},{"x":4,"y":-2},{"x":7,"y":-2}]},{"index":2,"tiles":[{"x":1.5,"y":-9},{"x":2.5,"y":-9},{"x":3.5,"y":-9},{"x":5.5,"y":-9},{"x":7.5,"y":-9},{"x":8.5,"y":-9},{"x":9.5,"y":-9},{"x":4.5,"y":-8.5},{"x":6.5,"y":-8.5},{"x":3.5,"y":-8},{"x":5.5,"y":-8},{"x":7.5,"y":-8},{"x":2.5,"y":-7.5},{"x":8.5,"y":-7.5},{"x":1.5,"y":-7},{"x":5.5,"y":-7},{"x":9.5,"y":-7},{"x":5.5,"y":-6},{"x":4.5,"y":-5.5},{"x":6.5,"y":-5.5},{"x":3.5,"y":-5},{"x":5.5,"y":-5},{"x":7.5,"y":-5},{"x":2.5,"y":-4.5},{"x":8.5,"y":-4.5},{"x":5,"y":-4},{"x":6,"y":-4},{"x":2,"y":-3.5},{"x":9,"y":-3.5},{"x":4.5,"y":-3},{"x":6.5,"y":-3},{"x":4,"y":-2},{"x":7,"y":-2}]}],"seeds":["IeYZVJVyQxg2YnOYlDEKWeF1YMVkHuYUjsdMz6NQgbJYXAh6IkRdHNM14YVyYhB6mRBa4EGUX9B93jRApwgu3pVxYcMRAXmpHQMA"]},{"layers":[{"index":0,"tiles":[{"x":1.5,"y":-9},{"x":2.5,"y":-9},{"x":3.5,"y":-9},{"x":4.5,"y":-9},{"x":5.5,"y":-9},{"x":6.5,"y":-9},{"x":8.5,"y":-9},{"x":9.5,"y":-9},{"x":1.5,"y":-8},{"x":2.5,"y":-8},{"x":3.5,"y":-8},{"x":4.5,"y":-8},{"x":5.5,"y":-8},{"x":7.5,"y":-8},{"x":8.5,"y":-8},{"x":9.5,"y":-8},{"x":1.5,"y":-7},{"x":2.5,"y":-7},{"x":3.5,"y":-7},{"x":4.5,"y":-7},{"x":6.5,"y":-7},{"x":7.5,"y":-7},{"x":8.5,"y":-7},{"x":1.5,"y":-6},{"x":2.5,"y":-6},{"x":3.5,"y":-6},{"x":5.5,"y":-6},{"x":6.5,"y":-6},{"x":7.5,"y":-6},{"x":9.5,"y":-6},{"x":1.5,"y":-5},{"x":2.5,"y":-5},{"x":4.5,"y":-5},{"x":5.5,"y":-5},{"x":6.5,"y":-5},{"x":8.5,"y":-5},{"x":9.5,"y":-5},{"x":1.5,"y":-4},{"x":3.5,"y":-4},{"x":4.5,"y":-4},{"x":5.5,"y":-4},{"x":7.5,"y":-4},{"x":8.5,"y":-4},{"x":9.5,"y":-4},{"x":2.5,"y":-3},{"x":3.5,"y":-3},{"x":4.5,"y":-3},{"x":6.5,"y":-3},{"x":7.5,"y":-3},{"x":8.5,"y":-3},{"x":9.5,"y":-3},{"x":1.5,"y":-2},{"x":2.5,"y":-2},{"x":3.5,"y":-2},{"x":5.5,"y":-2},{"x":6.5,"y":-2},{"x":7.5,"y":-2},{"x":8.5,"y":-2},{"x":9.5,"y":-2},{"x":1.5,"y":-1},{"x":2.5,"y":-1},{"x":4.5,"y":-1},{"x":5.5,"y":-1},{"x":6.5,"y":-1},{"x":7.5,"y":-1},{"x":8.5,"y":-1},{"x":9.5,"y":-1}]},{"index":1,"tiles":[{"x":1.5,"y":-9},{"x":2.5,"y":-9},{"x":3.5,"y":-9},{"x":4.5,"y":-9},{"x":5.5,"y":-9},{"x":6.5,"y":-9},{"x":8.5,"y":-9},{"x":9.5,"y":-9},{"x":1.5,"y":-8},{"x":2.5,"y":-8},{"x":3.5,"y":-8},{"x":4.5,"y":-8},{"x":5.5,"y":-8},{"x":7.5,"y":-8},{"x":8.5,"y":-8},{"x":9.5,"y":-8},{"x":1.5,"y":-7},{"x":2.5,"y":-7},{"x":3.5,"y":-7},{"x":4.5,"y":-7},{"x":6.5,"y":-7},{"x":7.5,"y":-7},{"x":8.5,"y":-7},{"x":1.5,"y":-6},{"x":2.5,"y":-6},{"x":3.5,"y":-6},{"x":5.5,"y":-6},{"x":6.5,"y":-6},{"x":7.5,"y":-6},{"x":9.5,"y":-6},{"x":1.5,"y":-5},{"x":2.5,"y":-5},{"x":4.5,"y":-5},{"x":5.5,"y":-5},{"x":6.5,"y":-5},{"x":8.5,"y":-5},{"x":9.5,"y":-5},{"x":1.5,"y":-4},{"x":3.5,"y":-4},{"x":4.5,"y":-4},{"x":5.5,"y":-4},{"x":7.5,"y":-4},{"x":8.5,"y":-4},{"x":9.5,"y":-4},{"x":2.5,"y":-3},{"x":3.5,"y":-3},{"x":4.5,"y":-3},{"x":6.5,"y":-3},{"x":7.5,"y":-3},{"x":8.5,"y":-3},{"x":9.5,"y":-3},{"x":1.5,"y":-2},{"x":2.5,"y":-2},{"x":3.5,"y":-2},{"x":5.5,"y":-2},{"x":6.5,"y":-2},{"x":7.5,"y":-2},{"x":8.5,"y":-2},{"x":9.5,"y":-2},{"x":1.5,"y":-1},{"x":2.5,"y":-1},{"x":4.5,"y":-1},{"x":5.5,"y":-1},{"x":6.5,"y":-1},{"x":7.5,"y":-1},{"x":8.5,"y":-1},{"x":9.5,"y":-1}]}],"seeds":["j+cwKvMdisB5XRFBIKg42NKBHteIXoiFzBY+2wCG4Nl50iFwVpNlQhiK2kSIX0AQnyJSYBU1pSFeV5BwoiAun8VNnZFATcp1n9QFSzANYUWFVfUh2gJSjIWQ5igqAzV5xACiVgEA"]},{"layers":[{"index":0,"tiles":[{"x":5,"y":-9},{"x":6,"y":-9},{"x":4,"y":-8.5},{"x":7,"y":-8.5},{"x":2,"y":-8},{"x":3,"y":-8},{"x":5,"y":-8},{"x":6,"y":-8},{"x":8,"y":-8},{"x":9,"y":-8},{"x":1.5,"y":-7},{"x":2.5,"y":-7},{"x":5.5,"y":-7},{"x":8.5,"y":-7},{"x":9.5,"y":-7},{"x":1,"y":-6},{"x":2,"y":-6},{"x":3,"y":-6},{"x":5,"y":-6},{"x":6,"y":-6},{"x":8,"y":-6},{"x":9,"y":-6},{"x":10,"y":-6},{"x":0.5,"y":-5},{"x":1.5,"y":-5},{"x":2.5,"y":-5},{"x":3.5,"y":-5},{"x":4.5,"y":-5},{"x":5.5,"y":-5},{"x":6.5,"y":-5},{"x":7.5,"y":-5},{"x":8.5,"y":-5},{"x":9.5,"y":-5},{"x":10.5,"y":-5},{"x":1,"y":-4},{"x":2,"y":-4},{"x":3,"y":-4},{"x":5,"y":-4},{"x":6,"y":-4},{"x":8,"y":-4},{"x":9,"y":-4},{"x":10,"y":-4},{"x":1.5,"y":-3},{"x":2.5,"y":-3},{"x":5.5,"y":-3},{"x":8.5,"y":-3},{"x":9.5,"y":-3},{"x":2,"y":-2},{"x":3,"y":-2},{"x":5,"y":-2},{"x":6,"y":-2},{"x":8,"y":-2},{"x":9,"y":-2},{"x":4,"y":-1.5},{"x":7,"y":-1.5},{"x":5,"y":-1},{"x":6,"y":-1}]},{"index":1,"tiles":[{"x":5,"y":-9},{"x":6,"y":-9},{"x":4,"y":-8.5},{"x":7,"y":-8.5},{"x":2,"y":-8},{"x":3,"y":-8},{"x":5,"y":-8},{"x":6,"y":-8},{"x":8,"y":-8},{"x":9,"y":-8},{"x":1.5,"y":-7},{"x":2.5,"y":-7},{"x":5.5,"y":-7},{"x":8.5,"y":-7},{"x":9.5,"y":-7},{"x":1,"y":-6},{"x":2,"y":-6},{"x":3,"y":-6},{"x":5,"y":-6},{"x":6,"y":-6},{"x":8,"y":-6},{"x":9,"y":-6},{"x":10,"y":-6},{"x":0.5,"y":-5},{"x":1.5,"y":-5},{"x":2.5,"y":-5},{"x":3.5,"y":-5},{"x":4.5,"y":-5},{"x":5.5,"y":-5},{"x":6.5,"y":-5},{"x":7.5,"y":-5},{"x":8.5,"y":-5},{"x":9.5,"y":-5},{"x":10.5,"y":-5},{"x":1,"y":-4},{"x":2,"y":-4},{"x":3,"y":-4},{"x":5,"y":-4},{"x":6,"y":-4},{"x":8,"y":-4},{"x":9,"y":-4},{"x":10,"y":-4},{"x":1.5,"y":-3},{"x":2.5,"y":-3},{"x":5.5,"y":-3},{"x":8.5,"y":-3},{"x":9.5,"y":-3},{"x":2,"y":-2},{"x":3,"y":-2},{"x":5,"y":-2},{"x":6,"y":-2},{"x":8,"y":-2},{"x":9,"y":-2},{"x":4,"y":-1.5},{"x":7,"y":-1.5},{"x":5,"y":-1},{"x":6,"y":-1}]}],"seeds":["SjiJ0YIJQ0diKGU0oqQREbRkyfEQGyiCUwpy5oE4XjeFoHRxWehNgtGJxRcoIKOEWicmKkiBHvRZXPFxSzhYFDVyXCAspddVjHCJAfKEzXdWm9MFCggA"]},{"layers":[{"index":0,"tiles":[{"x":2,"y":-8.5},{"x":4,"y":-8.5},{"x":7,"y":-8.5},{"x":9,"y":-8.5},{"x":3,"y":-8},{"x":5.5,"y":-8},{"x":8,"y":-8},{"x":2,"y":-7.5},{"x":9,"y":-7.5},{"x":4.5,"y":-7},{"x":6.5,"y":-7},{"x":2,"y":-6.5},{"x":9,"y":-6.5},{"x":3,"y":-6},{"x":8,"y":-6},{"x":2,"y":-5.5},{"x":4,"y":-5.5},{"x":7,"y":-5.5},{"x":9,"y":-5.5},{"x":2,"y":-4.5},{"x":4,"y":-4.5},{"x":7,"y":-4.5},{"x":9,"y":-4.5},{"x":3,"y":-4},{"x":8,"y":-4},{"x":2,"y":-3.5},{"x":9,"y":-3.5},{"x":4.5,"y":-3},{"x":6.5,"y":-3},{"x":2,"y":-2.5},{"x":9,"y":-2.5},{"x":3,"y":-2},{"x":5.5,"y":-2},{"x":8,"y":-2},{"x":2,"y":-1.5},{"x":4,"y":-1.5},{"x":7,"y":-1.5},{"x":9,"y":-1.5}]},{"index":1,"tiles":[{"x":5.5,"y":-8},{"x":3,"y":-7.5},{"x":8,"y":-7.5},{"x":4.5,"y":-7},{"x":6.5,"y":-7},{"x":3,"y":-6.5},{"x":8,"y":-6.5},{"x":3,"y":-5.5},{"x":8,"y":-5.5},{"x":4.5,"y":-5},{"x":6.5,"y":-5},{"x":3,"y":-4.5},{"x":8,"y":-4.5},{"x":3,"y":-3.5},{"x":8,"y":-3.5},{"x":4.5,"y":-3},{"x":6.5,"y":-3},{"x":3,"y":-2.5},{"x":8,"y":-2.5},{"x":5.5,"y":-2}]},{"index":2,"tiles":[{"x":3.5,"y":-7.5},{"x":7.5,"y":-7.5},{"x":4.5,"y":-7},{"x":6.5,"y":-7},{"x":3.5,"y":-6.5},{"x":7.5,"y":-6.5},{"x":3.5,"y":-5.5},{"x":7.5,"y":-5.5},{"x":5,"y":-5},{"x":6,"y":-5},{"x":3.5,"y":-4.5},{"x":7.5,"y":-4.5},{"x":3.5,"y":-3.5},{"x":7.5,"y":-3.5},{"x":4.5,"y":-3},{"x":6.5,"y":-3},{"x":3.5,"y":-2.5},{"x":7.5,"y":-2.5}]},{"index":3,"tiles":[{"x":4,"y":-7},{"x":5,"y":-7},{"x":6,"y":-7},{"x":7,"y":-7},{"x":4,"y":-5},{"x":5,"y":-5},{"x":6,"y":-5},{"x":7,"y":-5},{"x":4,"y":-3},{"x":5,"y":-3},{"x":6,"y":-3},{"x":7,"y":-3}]}],"seeds":["AQOJ3CJmAkSJiBKWHhNlZ9AIRmp4QwNmXudgIniI3VBxXEdUGPI8IakUx2cuhRpSDjGNIniBUQhyF5pNlmeJnfiB"]},{"layers":[{"index":0,"tiles":[{"x":4.5,"y":-9.5},{"x":5.5,"y":-9.5},{"x":3.5,"y":-9},{"x":6.5,"y":-9},{"x":2.5,"y":-8.5},{"x":7.5,"y":-8.5},{"x":2,"y":-7.5},{"x":6,"y":-7.5},{"x":7,"y":-7.5},{"x":8,"y":-7.5},{"x":5,"y":-7},{"x":1.5,"y":-6.5},{"x":4,"y":-6.5},{"x":8.5,"y":-6.5},{"x":1.5,"y":-5.5},{"x":3.5,"y":-5.5},{"x":8.5,"y":-5.5},{"x":9.5,"y":-5.5},{"x":2,"y":-4.5},{"x":3,"y":-4.5},{"x":8,"y":-4.5},{"x":10,"y":-4.5},{"x":2.5,"y":-3.5},{"x":7.5,"y":-3.5},{"x":10,"y":-3.5},{"x":3.5,"y":-3},{"x":6.5,"y":-3},{"x":4.5,"y":-2.5},{"x":5.5,"y":-2.5},{"x":9.5,"y":-2.5},{"x":4,"y":-1.5},{"x":9,"y":-1.5},{"x":5,"y":-1},{"x":8,"y":-1},{"x":6,"y":-0.5},{"x":7,"y":-0.5}]},{"index":1,"tiles":[{"x":4.5,"y":-9.5},{"x":5.5,"y":-9.5},{"x":3.5,"y":-9},{"x":6.5,"y":-9},{"x":2.5,"y":-8.5},{"x":7.5,"y":-8.5},{"x":2,"y":-7.5},{"x":6,"y":-7.5},{"x":7,"y":-7.5},{"x":5,"y":-7},{"x":8,"y":-7},{"x":1.5,"y":-6.5},{"x":4,"y":-6.5},{"x":9,"y":-6.5},{"x":1.5,"y":-5.5},{"x":3.5,"y":-5.5},{"x":8.5,"y":-5.5},{"x":9.5,"y":-5.5},{"x":2,"y":-4.5},{"x":3,"y":-4.5},{"x":8,"y":-4.5},{"x":10,"y":-4.5},{"x":3,"y":-3.5},{"x":7.5,"y":-3.5},{"x":10,"y":-3.5},{"x":6.5,"y":-3},{"x":3.5,"y":-2.5},{"x":4.5,"y":-2.5},{"x":5.5,"y":-2.5},{"x":9.5,"y":-2.5},{"x":4,"y":-1.5},{"x":9,"y":-1.5},{"x":5,"y":-1},{"x":8,"y":-1},{"x":6,"y":-0.5},{"x":7,"y":-0.5}]},{"index":2,"tiles":[{"x":4.5,"y":-9.5},{"x":5.5,"y":-9.5},{"x":3.5,"y":-9},{"x":6.5,"y":-9},{"x":2.5,"y":-8.5},{"x":7.5,"y":-8.5},{"x":2,"y":-7.5},{"x":8,"y":-7.5},{"x":1.5,"y":-6.5},{"x":8.5,"y":-6.5},{"x":1.5,"y":-5.5},{"x":8.5,"y":-5.5},{"x":2,"y":-4.5},{"x":8,"y":-4.5},{"x":2.5,"y":-3.5},{"x":7.5,"y":-3.5},{"x":3.5,"y":-3},{"x":6.5,"y":-3},{"x":4.5,"y":-2.5},{"x":5.5,"y":-2.5}]}],"seeds":["nMY5zseh2HOFDfkxn3YSk+gdw9eJobEIQnhwnwdSxRheolWJAVVMjbJYncoxn5FBxMMF4ICVIKJ0VdSZCAiBXgimXhZG"]},{"layers":[{"index":0,"tiles":[{"x":5.5,"y":-8.5},{"x":4.5,"y":-8},{"x":6.5,"y":-8},{"x":1.5,"y":-7.5},{"x":3.5,"y":-7.5},{"x":5.5,"y":-7.5},{"x":7.5,"y":-7.5},{"x":9.5,"y":-7.5},{"x":0.5,"y":-7},{"x":2.5,"y":-7},{"x":4.5,"y":-7},{"x":6.5,"y":-7},{"x":8.5,"y":-7},{"x":10.5,"y":-7},{"x":1.5,"y":-6.5},{"x":3.5,"y":-6.5},{"x":5.5,"y":-6.5},{"x":7.5,"y":-6.5},{"x":9.5,"y":-6.5},{"x":0.5,"y":-6},{"x":2.5,"y":-6},{"x":4.5,"y":-6},{"x":6.5,"y":-6},{"x":8.5,"y":-6},{"x":10.5,"y":-6},{"x":1.5,"y":-5.5},{"x":3.5,"y":-5.5},{"x":5.5,"y":-5.5},{"x":7.5,"y":-5.5},{"x":9.5,"y":-5.5},{"x":0.5,"y":-5},{"x":2.5,"y":-5},{"x":4.5,"y":-5},{"x":6.5,"y":-5},{"x":8.5,"y":-5},{"x":10.5,"y":-5},{"x":1.5,"y":-4.5},{"x":3.5,"y":-4.5},{"x":5.5,"y":-4.5},{"x":7.5,"y":-4.5},{"x":9.5,"y":-4.5},{"x":0.5,"y":-4},{"x":2.5,"y":-4},{"x":4.5,"y":-4},{"x":6.5,"y":-4},{"x":8.5,"y":-4},{"x":10.5,"y":-4},{"x":1.5,"y":-3.5},{"x":3.5,"y":-3.5},{"x":5.5,"y":-3.5},{"x":7.5,"y":-3.5},{"x":9.5,"y":-3.5},{"x":0.5,"y":-3},{"x":2.5,"y":-3},{"x":4.5,"y":-3},{"x":6.5,"y":-3},{"x":8.5,"y":-3},{"x":10.5,"y":-3},{"x":1.5,"y":-2.5},{"x":3.5,"y":-2.5},{"x":5.5,"y":-2.5},{"x":7.5,"y":-2.5},{"x":9.5,"y":-2.5},{"x":4.5,"y":-2},{"x":6.5,"y":-2},{"x":5.5,"y":-1.5}]},{"index":1,"tiles":[{"x":4.5,"y":-8},{"x":6.5,"y":-8},{"x":1.5,"y":-7.5},{"x":3.5,"y":-7.5},{"x":5.5,"y":-7.5},{"x":7.5,"y":-7.5},{"x":9.5,"y":-7.5},{"x":0.5,"y":-7},{"x":2.5,"y":-7},{"x":4.5,"y":-7},{"x":6.5,"y":-7},{"x":8.5,"y":-7},{"x":10.5,"y":-7},{"x":3.5,"y":-6.5},{"x":7.5,"y":-6.5},{"x":0.5,"y":-6},{"x":2.5,"y":-6},{"x":4.5,"y":-6},{"x":6.5,"y":-6},{"x":8.5,"y":-6},{"x":10.5,"y":-6},{"x":1.5,"y":-5.5},{"x":5.5,"y":-5.5},{"x":9.5,"y":-5.5},{"x":0.5,"y":-5},{"x":10.5,"y":-5},{"x":1.5,"y":-4.5},{"x":5.5,"y":-4.5},{"x":9.5,"y":-4.5},{"x":0.5,"y":-4},{"x":2.5,"y":-4},{"x":4.5,"y":-4},{"x":6.5,"y":-4},{"x":8.5,"y":-4},{"x":10.5,"y":-4},{"x":3.5,"y":-3.5},{"x":7.5,"y":-3.5},{"x":0.5,"y":-3},{"x":2.5,"y":-3},{"x":4.5,"y":-3},{"x":6.5,"y":-3},{"x":8.5,"y":-3},{"x":10.5,"y":-3},{"x":1.5,"y":-2.5},{"x":3.5,"y":-2.5},{"x":5.5,"y":-2.5},{"x":7.5,"y":-2.5},{"x":9.5,"y":-2.5},{"x":4.5,"y":-2},{"x":6.5,"y":-2}]}],"seeds":["ntEEj4Z5yVcuAdcNHAFKHmV51sREGMipwVJxpuhsyyQKBtR8IoOGm6QIXBg8HRKC4EgS2aGAYgKGXPeFR9dll3IOHgVORRpdVFeIkAB6GlIJi+h8ExUq"]},{"layers":[{"index":0,"tiles":[{"x":2.5,"y":-9.5},{"x":8.5,"y":-9.5},{"x":1.5,"y":-9},{"x":3.5,"y":-9},{"x":5.5,"y":-9},{"x":7.5,"y":-9},{"x":9.5,"y":-9},{"x":2.5,"y":-8.5},{"x":8.5,"y":-8.5},{"x":1.5,"y":-8},{"x":3.5,"y":-8},{"x":5.5,"y":-8},{"x":7.5,"y":-8},{"x":9.5,"y":-8},{"x":2.5,"y":-7.5},{"x":4.5,"y":-7.5},{"x":6.5,"y":-7.5},{"x":8.5,"y":-7.5},{"x":1.5,"y":-7},{"x":3.5,"y":-7},{"x":7.5,"y":-7},{"x":9.5,"y":-7},{"x":2.5,"y":-6.5},{"x":4.5,"y":-6.5},{"x":6.5,"y":-6.5},{"x":8.5,"y":-6.5},{"x":1.5,"y":-6},{"x":3.5,"y":-6},{"x":5.5,"y":-6},{"x":7.5,"y":-6},{"x":9.5,"y":-6},{"x":2.5,"y":-5.5},{"x":8.5,"y":-5.5},{"x":1.5,"y":-5},{"x":3.5,"y":-5},{"x":5.5,"y":-5},{"x":7.5,"y":-5},{"x":9.5,"y":-5},{"x":2.5,"y":-4.5},{"x":4.5,"y":-4.5},{"x":6.5,"y":-4.5},{"x":8.5,"y":-4.5},{"x":1.5,"y":-4},{"x":3.5,"y":-4},{"x":7.5,"y":-4},{"x":9.5,"y":-4},{"x":2.5,"y":-3.5},{"x":4.5,"y":-3.5},{"x":6.5,"y":-3.5},{"x":8.5,"y":-3.5},{"x":1.5,"y":-3},{"x":3.5,"y":-3},{"x":5.5,"y":-3},{"x":7.5,"y":-3},{"x":9.5,"y":-3},{"x":2.5,"y":-2.5},{"x":8.5,"y":-2.5},{"x":1.5,"y":-2},{"x":3.5,"y":-2},{"x":5.5,"y":-2},{"x":7.5,"y":-2},{"x":9.5,"y":-2},{"x":2.5,"y":-1.5},{"x":8.5,"y":-1.5}]},{"index":1,"tiles":[{"x":4,"y":-9.5},{"x":7,"y":-9.5},{"x":2.5,"y":-9},{"x":5.5,"y":-9},{"x":8.5,"y":-9},{"x":1.5,"y":-8.5},{"x":3.5,"y":-8.5},{"x":7.5,"y":-8.5},{"x":9.5,"y":-8.5},{"x":2.5,"y":-8},{"x":5.5,"y":-8},{"x":8.5,"y":-8},{"x":1.5,"y":-7.5},{"x":3.5,"y":-7.5},{"x":4.5,"y":-7.5},{"x":6.5,"y":-7.5},{"x":7.5,"y":-7.5},{"x":9.5,"y":-7.5},{"x":2.5,"y":-7},{"x":8.5,"y":-7},{"x":1.5,"y":-6.5},{"x":3.5,"y":-6.5},{"x":4.5,"y":-6.5},{"x":6.5,"y":-6.5},{"x":7.5,"y":-6.5},{"x":9.5,"y":-6.5},{"x":2.5,"y":-6},{"x":5.5,"y":-6},{"x":8.5,"y":-6},{"x":1.5,"y":-5.5},{"x":3.5,"y":-5.5},{"x":7.5,"y":-5.5},{"x":9.5,"y":-5.5},{"x":2.5,"y":-5},{"x":5.5,"y":-5},{"x":8.5,"y":-5},{"x":1.5,"y":-4.5},{"x":3.5,"y":-4.5},{"x":4.5,"y":-4.5},{"x":6.5,"y":-4.5},{"x":7.5,"y":-4.5},{"x":9.5,"y":-4.5},{"x":2.5,"y":-4},{"x":8.5,"y":-4},{"x":1.5,"y":-3.5},{"x":3.5,"y":-3.5},{"x":4.5,"y":-3.5},{"x":6.5,"y":-3.5},{"x":7.5,"y":-3.5},{"x":9.5,"y":-3.5},{"x":2.5,"y":-3},{"x":5.5,"y":-3},{"x":8.5,"y":-3},{"x":1.5,"y":-2.5},{"x":3.5,"y":-2.5},{"x":7.5,"y":-2.5},{"x":9.5,"y":-2.5},{"x":2.5,"y":-2},{"x":5.5,"y":-2},{"x":8.5,"y":-2},{"x":4,"y":-1.5},{"x":7,"y":-1.5}]},{"index":2,"tiles":[{"x":3.5,"y":-9.5},{"x":4.5,"y":-9.5},{"x":6.5,"y":-9.5},{"x":7.5,"y":-9.5},{"x":5.5,"y":-9},{"x":3.5,"y":-8.5},{"x":7.5,"y":-8.5},{"x":5.5,"y":-8},{"x":3.5,"y":-7.5},{"x":4.5,"y":-7.5},{"x":6.5,"y":-7.5},{"x":7.5,"y":-7.5},{"x":3.5,"y":-6.5},{"x":4.5,"y":-6.5},{"x":6.5,"y":-6.5},{"x":7.5,"y":-6.5},{"x":5.5,"y":-6},{"x":3.5,"y":-5.5},{"x":7.5,"y":-5.5},{"x":5.5,"y":-5},{"x":3.5,"y":-4.5},{"x":4.5,"y":-4.5},{"x":6.5,"y":-4.5},{"x":7.5,"y":-4.5},{"x":3.5,"y":-3.5},{"x":4.5,"y":-3.5},{"x":6.5,"y":-3.5},{"x":7.5,"y":-3.5},{"x":5.5,"y":-3},{"x":3.5,"y":-2.5},{"x":7.5,"y":-2.5},{"x":5.5,"y":-2},{"x":3.5,"y":-1.5},{"x":4.5,"y":-1.5},{"x":6.5,"y":-1.5},{"x":7.5,"y":-1.5}]}],"seeds":["YNB50AWOw8ZYSuQU3hQ5HheK3MeBZmiAHlU1l4dUH/iJ1JkN6PBQGlJOV7iIHad0AxU+SiMuEiFWDLhImSCA2vIURlNsVuilgZgYGAgSYjB5DWdhD+M8aseAh9cdwReGRBByX8B9kKdxU9dVjlB0lpIYoSZ4Ikk84QUA"]},{"layers":[{"index":0,"tiles":[{"x":5.5,"y":-9},{"x":4,"y":-8.5},{"x":7,"y":-8.5},{"x":3,"y":-8},{"x":5,"y":-8},{"x":6,"y":-8},{"x":8,"y":-8},{"x":2,"y":-7.5},{"x":4,"y":-7.5},{"x":7,"y":-7.5},{"x":9,"y":-7.5},{"x":3,"y":-7},{"x":5.5,"y":-7},{"x":8,"y":-7},{"x":1.5,"y":-6.5},{"x":4,"y":-6.5},{"x":7,"y":-6.5},{"x":9.5,"y":-6.5},{"x":3,"y":-6},{"x":5,"y":-6},{"x":6,"y":-6},{"x":8,"y":-6},{"x":2,"y":-5.5},{"x":4,"y":-5.5},{"x":7,"y":-5.5},{"x":9,"y":-5.5},{"x":3,"y":-5},{"x":5.5,"y":-5},{"x":8,"y":-5},{"x":1.5,"y":-4.5},{"x":4.5,"y":-4.5},{"x":6.5,"y":-4.5},{"x":9.5,"y":-4.5},{"x":3.5,"y":-4},{"x":5.5,"y":-4},{"x":7.5,"y":-4},{"x":2,"y":-3.5},{"x":9,"y":-3.5},{"x":5,"y":-3},{"x":6,"y":-3},{"x":1.5,"y":-2.5},{"x":3.5,"y":-2.5},{"x":7.5,"y":-2.5},{"x":9.5,"y":-2.5},{"x":2.5,"y":-2},{"x":4.5,"y":-2},{"x":6.5,"y":-2},{"x":8.5,"y":-2},{"x":1.5,"y":-1.5},{"x":5.5,"y":-1.5},{"x":9.5,"y":-1.5}]},{"index":1,"tiles":[{"x":5.5,"y":-9},{"x":3.5,"y":-8.5},{"x":4.5,"y":-8.5},{"x":6.5,"y":-8.5},{"x":7.5,"y":-8.5},{"x":3,"y":-7.5},{"x":4,"y":-7.5},{"x":5,"y":-7.5},{"x":6,"y":-7.5},{"x":7,"y":-7.5},{"x":8,"y":-7.5},{"x":2,"y":-7},{"x":9,"y":-7},{"x":3,"y":-6.5},{"x":4,"y":-6.5},{"x":5,"y":-6.5},{"x":6,"y":-6.5},{"x":7,"y":-6.5},{"x":8,"y":-6.5},{"x":2,"y":-6},{"x":9,"y":-6},{"x":3,"y":-5.5},{"x":4,"y":-5.5},{"x":5,"y":-5.5},{"x":6,"y":-5.5},{"x":7,"y":-5.5},{"x":8,"y":-5.5},{"x":2,"y":-5},{"x":9,"y":-5},{"x":3.5,"y":-4.5},{"x":4.5,"y":-4.5},{"x":5.5,"y":-4.5},{"x":6.5,"y":-4.5},{"x":7.5,"y":-4.5},{"x":2.5,"y":-4},{"x":8.5,"y":-4},{"x":5,"y":-3.5},{"x":6,"y":-3.5},{"x":2,"y":-3},{"x":3,"y":-3},{"x":4,"y":-3},{"x":7,"y":-3},{"x":8,"y":-3},{"x":9,"y":-3},{"x":5.5,"y":-2.5}]},{"index":2,"tiles":[{"x":5.5,"y":-8.5},{"x":5.5,"y":-7.5},{"x":4.5,"y":-7},{"x":6.5,"y":-7},{"x":4.5,"y":-6},{"x":5.5,"y":-6},{"x":6.5,"y":-6},{"x":2.5,"y":-5},{"x":3.5,"y":-5},{"x":4.5,"y":-5},{"x":6.5,"y":-5},{"x":7.5,"y":-5},{"x":8.5,"y":-5},{"x":5.5,"y":-4.5},{"x":2.5,"y":-4},{"x":3.5,"y":-4},{"x":4.5,"y":-4},{"x":6.5,"y":-4},{"x":7.5,"y":-4},{"x":8.5,"y":-4}]}],"seeds":["Xad+XwhCF/c54gN6HGeFWqUYYFgMR/oIhgCGCCWCYwOGgiKRW8AlRPFdGtGISgItwxJ1h4iBZ4VwHdOJnsd5j9gxU5ZNnoeFDxeAn/SVnbA5ZhdxKKVY"]},{"layers":[{"index":0,"tiles":[{"x":4.5,"y":-9},{"x":5.5,"y":-9},{"x":6.5,"y":-9},{"x":4.5,"y":-8},{"x":5.5,"y":-8},{"x":6.5,"y":-8},{"x":4.5,"y":-7},{"x":5.5,"y":-7},{"x":6.5,"y":-7},{"x":4.5,"y":-6},{"x":5.5,"y":-6},{"x":6.5,"y":-6},{"x":4.5,"y":-5},{"x":5.5,"y":-5},{"x":6.5,"y":-5},{"x":4.5,"y":-4},{"x":5.5,"y":-4},{"x":6.5,"y":-4},{"x":2.5,"y":-3},{"x":3.5,"y":-3},{"x":4.5,"y":-3},{"x":5.5,"y":-3},{"x":6.5,"y":-3},{"x":7.5,"y":-3},{"x":8.5,"y":-3},{"x":1.5,"y":-2},{"x":2.5,"y":-2},{"x":3.5,"y":-2},{"x":4.5,"y":-2},{"x":5.5,"y":-2},{"x":6.5,"y":-2},{"x":7.5,"y":-2},{"x":8.5,"y":-2},{"x":9.5,"y":-2}]},{"index":1,"tiles":[{"x":4.5,"y":-9},{"x":5.5,"y":-9},{"x":6.5,"y":-9},{"x":4.5,"y":-8},{"x":5.5,"y":-8},{"x":6.5,"y":-8},{"x":4.5,"y":-7},{"x":5.5,"y":-7},{"x":6.5,"y":-7},{"x":4.5,"y":-6},{"x":5.5,"y":-6},{"x":6.5,"y":-6},{"x":4.5,"y":-5},{"x":5.5,"y":-5},{"x":6.5,"y":-5},{"x":4.5,"y":-4},{"x":5.5,"y":-4},{"x":6.5,"y":-4},{"x":2.5,"y":-3},{"x":3.5,"y":-3},{"x":4.5,"y":-3},{"x":5.5,"y":-3},{"x":6.5,"y":-3},{"x":7.5,"y":-3},{"x":8.5,"y":-3},{"x":1.5,"y":-2},{"x":2.5,"y":-2},{"x":3.5,"y":-2},{"x":4.5,"y":-2},{"x":5.5,"y":-2},{"x":6.5,"y":-2},{"x":7.5,"y":-2},{"x":8.5,"y":-2},{"x":9.5,"y":-2}]},{"index":2,"tiles":[{"x":4.5,"y":-9},{"x":5.5,"y":-9},{"x":6.5,"y":-9},{"x":4.5,"y":-8},{"x":5.5,"y":-8},{"x":6.5,"y":-8},{"x":4.5,"y":-7},{"x":5.5,"y":-7},{"x":6.5,"y":-7},{"x":4.5,"y":-6},{"x":5.5,"y":-6},{"x":6.5,"y":-6},{"x":4.5,"y":-5},{"x":5.5,"y":-5},{"x":6.5,"y":-5},{"x":4.5,"y":-4},{"x":5.5,"y":-4},{"x":6.5,"y":-4},{"x":2.5,"y":-3},{"x":3.5,"y":-3},{"x":4.5,"y":-3},{"x":5.5,"y":-3},{"x":6.5,"y":-3},{"x":7.5,"y":-3},{"x":8.5,"y":-3},{"x":2,"y":-2},{"x":3,"y":-2},{"x":4,"y":-2},{"x":5,"y":-2},{"x":6,"y":-2},{"x":7,"y":-2},{"x":8,"y":-2},{"x":9,"y":-2}]},{"index":3,"tiles":[{"x":4.5,"y":-9},{"x":5.5,"y":-8.5},{"x":6.5,"y":-8},{"x":4.5,"y":-7.5},{"x":5.5,"y":-7},{"x":6.5,"y":-6.5},{"x":4.5,"y":-6},{"x":5.5,"y":-5.5},{"x":6.5,"y":-5},{"x":4.5,"y":-4.5},{"x":5.5,"y":-4},{"x":2.5,"y":-3},{"x":3.5,"y":-3},{"x":4.5,"y":-3},{"x":5.5,"y":-3},{"x":6.5,"y":-3},{"x":7.5,"y":-3},{"x":8.5,"y":-3},{"x":2.5,"y":-2},{"x":3.5,"y":-2},{"x":4.5,"y":-2},{"x":5.5,"y":-2},{"x":6.5,"y":-2},{"x":7.5,"y":-2},{"x":8.5,"y":-2}]},{"index":4,"tiles":[{"x":3,"y":-2},{"x":4,"y":-2},{"x":5,"y":-2},{"x":6,"y":-2},{"x":7,"y":-2},{"x":8,"y":-2}]}],"seeds":["nOJhjOI44cGRU0d92RZOkHhMS1gi3pUJXROFY6MGXydSAyiAoJEaWxh6j+ItX0AhgaB1YhIlBVWFIoYSAcQsntYYUgBalxUaRSgq3XSGYMgp5tOBVQgOksCBYhA2C/dxIaF4"]},{"layers":[{"index":0,"tiles":[{"x":5.5,"y":-9},{"x":4.5,"y":-8.5},{"x":6.5,"y":-8.5},{"x":5.5,"y":-8},{"x":2,"y":-7.5},{"x":4.5,"y":-7.5},{"x":6.5,"y":-7.5},{"x":9,"y":-7.5},{"x":1,"y":-7},{"x":3,"y":-7},{"x":5.5,"y":-7},{"x":8,"y":-7},{"x":10,"y":-7},{"x":2,"y":-6.5},{"x":4.5,"y":-6.5},{"x":6.5,"y":-6.5},{"x":9,"y":-6.5},{"x":1,"y":-6},{"x":3,"y":-6},{"x":5.5,"y":-6},{"x":8,"y":-6},{"x":10,"y":-6},{"x":2,"y":-5.5},{"x":4.5,"y":-5.5},{"x":6.5,"y":-5.5},{"x":9,"y":-5.5},{"x":1,"y":-5},{"x":3,"y":-5},{"x":5.5,"y":-5},{"x":8,"y":-5},{"x":10,"y":-5},{"x":2,"y":-4.5},{"x":4,"y":-4.5},{"x":7,"y":-4.5},{"x":9,"y":-4.5},{"x":1,"y":-4},{"x":3,"y":-4},{"x":5,"y":-4},{"x":6,"y":-4},{"x":8,"y":-4},{"x":10,"y":-4},{"x":2,"y":-3.5},{"x":4,"y":-3.5},{"x":7,"y":-3.5},{"x":9,"y":-3.5},{"x":1,"y":-3},{"x":3,"y":-3},{"x":5,"y":-3},{"x":6,"y":-3},{"x":8,"y":-3},{"x":10,"y":-3},{"x":2,"y":-2.5},{"x":4,"y":-2.5},{"x":7,"y":-2.5},{"x":9,"y":-2.5},{"x":5,"y":-2},{"x":6,"y":-2}]},{"index":1,"tiles":[{"x":5,"y":-8.5},{"x":6,"y":-8.5},{"x":5,"y":-7.5},{"x":6,"y":-7.5},{"x":1.5,"y":-7},{"x":2.5,"y":-7},{"x":8.5,"y":-7},{"x":9.5,"y":-7},{"x":5,"y":-6.5},{"x":6,"y":-6.5},{"x":1.5,"y":-6},{"x":2.5,"y":-6},{"x":8.5,"y":-6},{"x":9.5,"y":-6},{"x":5,"y":-5.5},{"x":6,"y":-5.5},{"x":1.5,"y":-5},{"x":2.5,"y":-5},{"x":8.5,"y":-5},{"x":9.5,"y":-5},{"x":5.5,"y":-4.5},{"x":1.5,"y":-4},{"x":2.5,"y":-4},{"x":4.5,"y":-4},{"x":6.5,"y":-4},{"x":8.5,"y":-4},{"x":9.5,"y":-4},{"x":3.5,"y":-3.5},{"x":5.5,"y":-3.5},{"x":7.5,"y":-3.5},{"x":1.5,"y":-3},{"x":2.5,"y":-3},{"x":4.5,"y":-3},{"x":6.5,"y":-3},{"x":8.5,"y":-3},{"x":9.5,"y":-3},{"x":5.5,"y":-2.5}]},{"index":2,"tiles":[{"x":5.5,"y":-4},{"x":4.5,"y":-3.5},{"x":6.5,"y":-3.5},{"x":5.5,"y":-3}]}],"seeds":["aDU0nqhQBEI1qTdOC1h8nMZkIBaFIqddR/RI4aQcoZF8TtJZIuFhZAAG3OCE59eVHXIJogAxoCgWIddxS5htGwdapiqBkPFVjwcA"]}]